{
  "<PAD>": 0,
  "<UNK>": 1,
  "کا": 2,
  "می": 3,
  "کی": 4,
  "سا": 5,
  "اور": 6,
  "کہ": 7,
  "کو": 8,
  "نا": 9,
  "پر": 10,
  "ہا": 11,
  "کر": 12,
  "اس": 13,
  "ہی": 14,
  "NUM": 15,
  "ایک": 16,
  "بھی": 17,
  "لیا": 18,
  "یہ": 19,
  "وہ": 20,
  "ان": 21,
  "ہو": 22,
  "تھا": 23,
  "نہی": 24,
  "کیا": 25,
  "سی": 26,
  "رہا": 27,
  "بی": 28,
  "پاکست": 29,
  "کرتا": 30,
  "تو": 31,
  "جا": 32,
  "گا": 33,
  "ہوا": 34,
  "جو": 35,
  "والا": 36,
  "بعد": 37,
  "انھ": 38,
  "کہا": 39,
  "ساتھ": 40,
  "بات": 41,
  "جس": 42,
  "انڈا": 43,
  "اپ": 44,
  "ہوت": 45,
  "گیا": 46,
  "بار": 47,
  "زیادہ": 48,
  "کہن": 49,
  "تک": 50,
  "ذریعہ": 51,
  "طور": 52,
  "مطابق": 53,
  "سکت": 54,
  "آا": 55,
  "اپن": 56,
  "سب": 57,
  "پی": 58,
  "دیا": 59,
  "لیکن": 60,
  "یا": 61,
  "ایس": 62,
  "نہ": 63,
  "کہت": 64,
  "دو": 65,
  "تھی": 66,
  "پہ": 67,
  "استعمال": 68,
  "کچھ": 69,
  "کھلاڑ": 70,
  "حاصل": 71,
  "کم": 72,
  "جب": 73,
  "ہے": 74,
  "کسی": 75,
  "شامل": 76,
  "ٹی": 77,
  "وقت": 78,
  "کرکٹ": 79,
  "آپ": 80,
  "رہی": 81,
  "دی": 82,
  "ہیں": 83,
  "دور": 84,
  "دیش": 85,
  "بتاا": 86,
  "بنگلہ": 87,
  "بنا": 88,
  "اسا": 89,
  "نام": 90,
  "سام": 91,
  "دوسر": 92,
  "کرن": 93,
  "لا": 94,
  "بڑا": 95,
  "اب": 96,
  "بہت": 97,
  "تعلق": 98,
  "ٹیم": 99,
  "ای": 100,
  "لوگ": 101,
  "حکومت": 102,
  "صرف": 103,
  "موجود": 104,
  "سال": 105,
  "وجہ": 106,
  "جی": 107,
  "اگر": 108,
  "جات": 109,
  "جبکہ": 110,
  "اا": 111,
  "انڈین": 112,
  "دون": 113,
  "کام": 114,
  "ہم": 115,
  "دن": 116,
  "خلاف": 117,
  "جانب": 118,
  "عمر": 119,
  "خان": 120,
  "رکھ": 121,
  "میڈا": 122,
  "جن": 123,
  "لکھ": 124,
  "پھر": 125,
  "ملک": 126,
  "لاکھ": 127,
  "جاتا": 128,
  "ہمار": 129,
  "کروڑ": 130,
  "دیکھ": 131,
  "حصہ": 132,
  "دنی": 133,
  "آباد": 134,
  "جائی": 135,
  "جنگ": 136,
  "ہوئا": 137,
  "میچ": 138,
  "کیونکہ": 139,
  "مزید": 140,
  "رکھت": 141,
  "روس": 142,
  "کوشش": 143,
  "میر": 144,
  "و": 145,
  "علاوہ": 146,
  "ایپسٹین": 147,
  "خبر": 148,
  "برس": 149,
  "نظر": 150,
  "الزام": 151,
  "حوالا": 152,
  "بڑی": 153,
  "کھیل": 154,
  "پاس": 155,
  "افغانست": 156,
  "ہر": 157,
  "کہان": 158,
  "علاق": 159,
  "ممالک": 160,
  "مقام": 161,
  "روپ": 162,
  "شاد": 163,
  "تین": 164,
  "کپ": 165,
  "مجھ": 166,
  "بن": 167,
  "صدر": 168,
  "دفاع": 169,
  "با": 170,
  "کمپن": 171,
  "دیگر": 172,
  "جار": 173,
  "طرف": 174,
  "طیار": 175,
  "قانون": 176,
  "سوشل": 177,
  "جہ": 178,
  "بیٹ": 179,
  "آنا": 180,
  "ایر": 181,
  "دا": 182,
  "مگر": 183,
  "صلاحیت": 184,
  "کار": 185,
  "کامیاب": 186,
  "تمام": 187,
  "شہر": 188,
  "دعو": 189,
  "حم": 190,
  "اسرائیل": 191,
  "تصویر": 192,
  "بلکہ": 193,
  "طرح": 194,
  "مواد": 195,
  "فوج": 196,
  "لگت": 197,
  "اردو": 198,
  "صارفین": 199,
  "ہا اس": 200,
  "ورلڈ": 201,
  "پاکستان": 202,
  "مشکل": 203,
  "آتا": 204,
  "درما": 205,
  "احمد": 206,
  "تقریب": 207,
  "پولیس": 208,
  "پیش": 209,
  "قبل": 210,
  "فون": 211,
  "ہ": 212,
  "سعود": 213,
  "فیصلہ": 214,
  "محمد": 215,
  "حکام": 216,
  "ایل": 217,
  "ہزار": 218,
  "طارق": 219,
  "چکا": 220,
  "سنہ": 221,
  "جان": 222,
  "سامن": 223,
  "گذشتہ": 224,
  "چاہت": 225,
  "پڑھ": 226,
  "بھر": 227,
  "ظاہر": 228,
  "عام": 229,
  "بند": 230,
  "گھر": 231,
  "تاہم": 232,
  "موقع": 233,
  "چند": 234,
  "شخص": 235,
  "قریب": 236,
  "تیار": 237,
  "قرار": 238,
  "بڑھ": 239,
  "مل": 240,
  "ٹرمپ": 241,
  "پہنچ": 242,
  "شروع": 243,
  "نیلام": 244,
  "زند": 245,
  "پانچ": 246,
  "کرا": 247,
  "دوست": 248,
  "نیوز": 249,
  "پڑا": 250,
  "عمل": 251,
  "عرب": 252,
  "فرور": 253,
  "واقع": 254,
  "فیچرز": 255,
  "یقین": 256,
  "آ": 257,
  "اجازت": 258,
  "میزائل": 259,
  "معلوم": 260,
  "غیر": 261,
  "عثم": 262,
  "اہم": 263,
  "پہل": 264,
  "لیگ": 265,
  "چھوٹ": 266,
  "اسلام": 267,
  "جنھ": 268,
  "امرا": 269,
  "حال": 270,
  "جگہ": 271,
  "ہون": 272,
  "تاکہ": 273,
  "ماہ": 274,
  "چار": 275,
  "شاہ": 276,
  "سرحد": 277,
  "لڑا": 278,
  "کبھ": 279,
  "چین": 280,
  "ہا ان": 281,
  "ہمی": 282,
  "جماعت": 283,
  "نقص": 284,
  "معاہد": 285,
  "معن": 286,
  "سبسکرائب": 287,
  "آٹھ": 288,
  "اچھ": 289,
  "طویل": 290,
  "معمول": 291,
  "کمی": 292,
  "آغاز": 293,
  "وزیر": 294,
  "گئی": 295,
  "دوبارہ": 296,
  "ختم": 297,
  "تھا وہ": 298,
  "لگا": 299,
  "بورڈ": 300,
  "امریکہ": 301,
  "سابق": 302,
  "ڈالر": 303,
  "عالم": 304,
  "سخت": 305,
  "اثر": 306,
  "ترین": 307,
  "صورتحال": 308,
  "رابطہ": 309,
  "اسی": 310,
  "ابھ": 311,
  "شدہ": 312,
  "آر": 313,
  "تفصیل": 314,
  "فلم": 315,
  "عوام": 316,
  "ضرور": 317,
  "کلک": 318,
  "تحت": 319,
  "ہا یہ": 320,
  "مضبوط": 321,
  "فراہم": 322,
  "مدد": 323,
  "ملازمت": 324,
  "ذریع": 325,
  "ڈیٹ": 326,
  "بل": 327,
  "سوال": 328,
  "جواب": 329,
  "جیل": 330,
  "پور": 331,
  "دیت": 332,
  "خاص": 333,
  "وال": 334,
  "عرص": 335,
  "علی": 336,
  "غزہ": 337,
  "بہتر": 338,
  "تعداد": 339,
  "ہا ،تصویر": 340,
  "شیئر": 341,
  "غلط": 342,
  "جسا": 343,
  "خود": 344,
  "ڈرون": 345,
  "فروخت": 346,
  "آخر": 347,
  "تیل": 348,
  "سری": 349,
  "بلا": 350,
  "باز": 351,
  "ہی انھ": 352,
  "کارروا": 353,
  "پتا": 354,
  "متعلق": 355,
  "مختلف": 356,
  "مقابلہ": 357,
  "سات": 358,
  "صحاف": 359,
  "بھیج": 360,
  "واضح": 361,
  "ڈاکٹر": 362,
  "این": 363,
  "اظہار": 364,
  "ایکس": 365,
  "جانا": 366,
  "گرد": 367,
  "گی": 368,
  "ادا": 369,
  "بجل": 370,
  "فیص": 371,
  "لی": 372,
  "فیصد": 373,
  "ایم": 374,
  "ہتھیار": 375,
  "رات": 376,
  "شاید": 377,
  "بتات": 378,
  "اللہ": 379,
  "کاف": 380,
  "گاڑ": 381,
  "پسند": 382,
  "الاقوام": 383,
  "رہت": 384,
  "طالب": 385,
  "بدل": 386,
  "افغ": 387,
  "راست": 388,
  "او": 389,
  "جنرل": 390,
  "رپورٹ": 391,
  "لن": 392,
  "نظام": 393,
  "ضرورت": 394,
  "را": 395,
  "خارجہ": 396,
  "ہی اس": 397,
  "مرکز": 398,
  "یعن": 399,
  "بول": 400,
  "از": 401,
  "مطلب": 402,
  "فضا": 403,
  "جہاز": 404,
  "خرید": 405,
  "لڑ": 406,
  "باہر": 407,
  "سلط": 408,
  "بچا": 409,
  "ہی ،تصویر": 410,
  "ایف": 411,
  "آزاد": 412,
  "خطرہ": 413,
  "روز": 414,
  "تبدیل": 415,
  "انداز": 416,
  "صحت": 417,
  "صارف": 418,
  "دکھا": 419,
  "آج": 420,
  "بنیاد": 421,
  "ملا": 422,
  "چاہا": 423,
  "پنجاب": 424,
  "یورپ": 425,
  "دس": 426,
  "تصاویر": 427,
  "خیال": 428,
  "بجا": 429,
  "ناکام": 430,
  "حالیہ": 431,
  "روک": 432,
  "الرحم": 433,
  "بین": 434,
  "ہی ان": 435,
  "آگا": 436,
  "زمین": 437,
  "پا": 438,
  "محبت": 439,
  "ٹوئنٹ": 440,
  "باعث": 441,
  "ترق": 442,
  "ذکر": 443,
  "بحث": 444,
  "پالیس": 445,
  "یہی": 446,
  "لینڈ": 447,
  "سلیم": 448,
  "افراد": 449,
  "جیس": 450,
  "قیمت": 451,
  "سالہ": 452,
  "افسر": 453,
  "ویب": 454,
  "سائٹ": 455,
  "دستاویز": 456,
  "سرد": 457,
  "سمجھ": 458,
  "چونکہ": 459,
  "ملاق": 460,
  "طا": 461,
  "فور": 462,
  "سرکار": 463,
  "گفتگو": 464,
  "بیمار": 465,
  "تھیں": 466,
  "رقم": 467,
  "حد": 468,
  "لگ": 469,
  "گرفتار": 470,
  "شفیق": 471,
  "قتل": 472,
  "ہی وہ": 473,
  "جنوب": 474,
  "محدود": 475,
  "سیاس": 476,
  "پید": 477,
  "قائم": 478,
  "آف": 479,
  "ذات": 480,
  "جنور": 481,
  "درج": 482,
  "ارب": 483,
  "مشرق": 484,
  "ایران": 485,
  "تصدیق": 486,
  "حمل": 487,
  "آفرید": 488,
  "چھ": 489,
  "برقرار": 490,
  "بھا": 491,
  "حمایت": 492,
  "ہا انھ": 493,
  "سیٹلائٹ": 494,
  "رہ": 495,
  "بغیر": 496,
  "فرنچائز": 497,
  "تھا ان": 498,
  "رنز": 499,
  "بعض": 500,
  "معاش": 501,
  "نوش": 502,
  "ما": 503,
  "کہی": 504,
  "ایکشن": 505,
  "ویڈیو": 506,
  "آئی": 507,
  "گزر": 508,
  "مستقبل": 509,
  "بقول": 510,
  "پتہ": 511,
  "چلت": 512,
  "سفر": 513,
  "کاروبار": 514,
  "انتخاب": 515,
  "ہا بی": 516,
  "خدم": 517,
  "رو": 518,
  "اصل": 519,
  "ملت": 520,
  "تجزیہ": 521,
  "خاتون": 522,
  "پرابووو": 523,
  "حفاظت": 524,
  "یوکرین": 525,
  "مقصد": 526,
  "انٹرویو": 527,
  "سطح": 528,
  "ہفت": 529,
  "ڈی": 530,
  "بچی": 531,
  "کیس": 532,
  "اعظم": 533,
  "میل": 534,
  "سکا": 535,
  "کردہ": 536,
  "عراق": 537,
  "مسئلہ": 538,
  "عدالت": 539,
  "پابند": 540,
  "میٹر": 541,
  "یو": 542,
  "پان": 543,
  "کانفرنس": 544,
  "گروہ": 545,
  "ہاتھ": 546,
  "معام": 547,
  "پریش": 548,
  "نکال": 549,
  "گر": 550,
  "مسلسل": 551,
  "چلا": 552,
  "تحریر": 553,
  "پوسٹ": 554,
  "سمندر": 555,
  "ہا وہ": 556,
  "پروگرام": 557,
  "شاہین": 558,
  "تھا انھ": 559,
  "عزیز": 560,
  "شدید": 561,
  "تاریخ": 562,
  "ہا لیکن": 563,
  "آس": 564,
  "چکی": 565,
  "شوہر": 566,
  "پتنگ": 567,
  "ابتدا": 568,
  "سکواڈ": 569,
  "واپس": 570,
  "نما": 571,
  "جیت": 572,
  "گا اس": 573,
  "وہی": 574,
  "تھا اس": 575,
  "رشتہ": 576,
  "تھا لیکن": 577,
  "درخواست": 578,
  "تحریک": 579,
  "منظور": 580,
  "بولنگ": 581,
  "وضاحت": 582,
  "آل": 583,
  "شمار": 584,
  "درست": 585,
  "تعین": 586,
  "فارم": 587,
  "حق": 588,
  "نکل": 589,
  "یونائیٹڈ": 590,
  "انتظامیہ": 591,
  "حوالہ": 592,
  "تجارت": 593,
  "ثابت": 594,
  "آرم": 595,
  "مید": 596,
  "جنس": 597,
  "نسل": 598,
  "تھی ،تصویر": 599,
  "سیاست": 600,
  "شک": 601,
  "محسوس": 602,
  "کھل": 603,
  "جانت": 604,
  "ہا تاہم": 605,
  "ہسپتال": 606,
  "ماہر": 607,
  "اندر": 608,
  "کولمبو": 609,
  "سٹیڈیم": 610,
  "روشن": 611,
  "دار": 612,
  "وکیل": 613,
  "والدین": 614,
  "رفتار": 615,
  "بچ": 616,
  "دیتا": 617,
  "گیند": 618,
  "کھڑ": 619,
  "تنقید": 620,
  "شرح": 621,
  "ورزش": 622,
  "دباؤ": 623,
  "کشت": 624,
  "زیر": 625,
  "فلسطین": 626,
  "احترام": 627,
  "مقدم": 628,
  "کروا": 629,
  "چیت": 630,
  "اعل": 631,
  "اہلکار": 632,
  "کھان": 633,
  "گریٹر": 634,
  "موت": 635,
  "بم": 636,
  "جلد": 637,
  "یاد": 638,
  "تحفظ": 639,
  "ادار": 640,
  "سوچ": 641,
  "حسن": 642,
  "اکثر": 643,
  "چینل": 644,
  "بیرون": 645,
  "اضافہ": 646,
  "ہی یہ": 647,
  "یاسر": 648,
  "سکیورٹ": 649,
  "جدید": 650,
  "مار": 651,
  "ماض": 652,
  "ویڈیوز": 653,
  "کردار": 654,
  "گرو": 655,
  "گزار": 656,
  "کلب": 657,
  "پیغام": 658,
  "تھا تاہم": 659,
  "تھا ،تصویر": 660,
  "بال": 661,
  "ڈور": 662,
  "درکار": 663,
  "خریدار": 664,
  "تھے": 665,
  "اتن": 666,
  "کن": 667,
  "تسلیم": 668,
  "مقاب": 669,
  "وکٹ": 670,
  "جذب": 671,
  "تنظیم": 672,
  "کارکرد": 673,
  "ٹیکنالوج": 674,
  "نتیج": 675,
  "احتجاج": 676,
  "شکار": 677,
  "سمیت": 678,
  "جاسوس": 679,
  "شناخت": 680,
  "کوئٹہ": 681,
  "براہ": 682,
  "ممکن": 683,
  "شائع": 684,
  "باضابطہ": 685,
  "ہا اسی": 686,
  "کیمر": 687,
  "راجاپکس": 688,
  "وائر": 689,
  "معیار": 690,
  "نہایت": 691,
  "سرمایہ": 692,
  "شق": 693,
  "لازم": 694,
  "میلز": 695,
  "سیزن": 696,
  "آیا": 697,
  "ذہن": 698,
  "آفیسر": 699,
  "ملزمہ": 700,
  "بحر": 701,
  "اشارہ": 702,
  "خطر": 703,
  "خاند": 704,
  "معامل": 705,
  "لگاا": 706,
  "دستیاب": 707,
  "قوم": 708,
  "ڈیلیور": 709,
  "مکمل": 710,
  "انتہا": 711,
  "دین": 712,
  "وزارت": 713,
  "تردید": 714,
  "دورہ": 715,
  "پلیٹ": 716,
  "بتا": 717,
  "متاثر": 718,
  "نظرا": 719,
  "جسمان": 720,
  "قواعد": 721,
  "اختیار": 722,
  "نائب": 723,
  "سفارت": 724,
  "سک": 725,
  "محض": 726,
  "رکاوٹ": 727,
  "حماس": 728,
  "نو": 729,
  "لطف": 730,
  "اندوز": 731,
  "کمر": 732,
  "اتحاد": 733,
  "لکھت": 734,
  "اچانک": 735,
  "وسط": 736,
  "آواز": 737,
  "دل": 738,
  "معاف": 739,
  "مشترکہ": 740,
  "خوراک": 741,
  "الفاظ": 742,
  "سرط": 743,
  "خون": 744,
  "جوڑ": 745,
  "لائن": 746,
  "نومبر": 747,
  "تقسیم": 748,
  "چاند": 749,
  "واقعہ": 750,
  "ڈیٹنگ": 751,
  "دہشت": 752,
  "بینک": 753,
  "اٹھ": 754,
  "لگی": 755,
  "عبداللہ": 756,
  "سکندر": 757,
  "رضا": 758,
  "نعیم": 759,
  "بولر": 760,
  "ندا": 761,
  "ریڈیو": 762,
  "عزام": 763,
  "متحدہ": 764,
  "ڈرونز": 765,
  "ہا پاکست": 766,
  "سٹیو": 767,
  "سمتھ": 768,
  "کراچ": 769,
  "سائن": 770,
  "فاروق": 771,
  "طریق": 772,
  "دیکھت": 773,
  "پیمنٹ": 774,
  "الحال": 775,
  "شریک": 776,
  "جمی": 777,
  "سنگھ": 778,
  "گرباز": 779,
  "منصوبہ": 780,
  "دلچسپ": 781,
  "ٹھیک": 782,
  "تار": 783,
  "رہنم": 784,
  "گے": 785,
  "وی": 786,
  "صبح": 787,
  "مظاہر": 788,
  "افریقہ": 789,
  "چیز": 790,
  "مارکیٹ": 791,
  "سچن": 792,
  "تنازع": 793,
  "ممکنہ": 794,
  "صورت": 795,
  "شیر": 796,
  "بڑھت": 797,
  "ہڑتال": 798,
  "اطلاع": 799,
  "ٹراف": 800,
  "کرس": 801,
  "نمائند": 802,
  "رشید": 803,
  "ہوں": 804,
  "منسلک": 805,
  "کتن": 806,
  "پکڑ": 807,
  "موقف": 808,
  "جورجا": 809,
  "نقشہ": 810,
  "یونین": 811,
  "دب": 812,
  "مسترد": 813,
  "تھا <NUM": 814,
  "عبور": 815,
  "ساز": 816,
  "منتقل": 817,
  "ضوابط": 818,
  "بھانو": 819,
  "انفراسٹرکچر": 820,
  "دھو": 821,
  "سینیئر": 822,
  "تکلیف": 823,
  "گا ان": 824,
  "لیت": 825,
  "ایونٹس": 826,
  "گہر": 827,
  "انصاف": 828,
  "بیشتر": 829,
  "مچل": 830,
  "راولپنڈ": 831,
  "عوض": 832,
  "کی اس": 833,
  "پریمیئر": 834,
  "شکل": 835,
  "ٹکڑ": 836,
  "کہہ": 837,
  "جائ": 838,
  "محکمہ": 839,
  "شام": 840,
  "تیز": 841,
  "میڈیکل": 842,
  "سینٹر": 843,
  "زائد": 844,
  "سار": 845,
  "جرم": 846,
  "ریکارڈ": 847,
  "پای": 848,
  "حقیقت": 849,
  "اقدام": 850,
  "بہترین": 851,
  "سبیانتو": 852,
  "فرانس": 853,
  "مبن": 854,
  "بیو": 855,
  "لندن": 856,
  "علامت": 857,
  "مسلم": 858,
  "ا": 859,
  "آپریشن": 860,
  "پریکٹس": 861,
  "پریماداس": 862,
  "اوق": 863,
  "انتظام": 864,
  "کس": 865,
  "قدر": 866,
  "دماغ": 867,
  "مند": 868,
  "ترتیب": 869,
  "اضاف": 870,
  "اگ": 871,
  "سولر": 872,
  "گرڈ": 873,
  "معاملہ": 874,
  "قدم": 875,
  "اسلحہ": 876,
  "تر": 877,
  "سپورٹس": 878,
  "دہائ": 879,
  "بیچ": 880,
  "ہی ایک": 881,
  "دسمبر": 882,
  "انسٹاگرام": 883,
  "سرگرم": 884,
  "چھات": 885,
  "نور": 886,
  "مسائل": 887,
  "راستہ": 888,
  "تارکین": 889,
  "وطن": 890,
  "داخل": 891,
  "مرتبہ": 892,
  "حملہ": 893,
  "ہاؤس": 894,
  "ڈال": 895,
  "ہمیشہ": 896,
  "کوہل": 897,
  "مقبول": 898,
  "زخم": 899,
  "طبی": 900,
  "متعدد": 901,
  "اگست": 902,
  "منسوب": 903,
  "ترجم": 904,
  "تصور": 905,
  "ہی بی": 906,
  "کمزور": 907,
  "عسکر": 908,
  "کارروائ": 909,
  "مشورہ": 910,
  "مسئ": 911,
  "نامہ": 912,
  "آگ": 913,
  "انس": 914,
  "دیں": 915,
  "ادوا": 916,
  "لڑی": 917,
  "اختلاف": 918,
  "انٹرنیشنل": 919,
  "کونسل": 920,
  "بٹ": 921,
  "تھی اس": 922,
  "سوار": 923,
  "باق": 924,
  "مبینہ": 925,
  "موجودہ": 926,
  "سر": 927,
  "ہٹا": 928,
  "سزا": 929,
  "قابل": 930,
  "حسین": 931,
  "سو": 932,
  "پڑت": 933,
  "سربراہ": 934,
  "برا": 935,
  "حصا": 936,
  "نعم": 937,
  "سود": 938,
  "ڈبلیو": 939,
  "آسان": 940,
  "نژاد": 941,
  "ہا لاہور": 942,
  "فاسٹ": 943,
  "مستفیض": 944,
  "وائرل": 945,
  "اداکار": 946,
  "اکاؤنٹ": 947,
  "اقوام": 948,
  "عائد": 949,
  "تباہ": 950,
  "ہا سب": 951,
  "ریسرچ": 952,
  "سپر": 953,
  "سیالکوٹ": 954,
  "کپت": 955,
  "لاہور": 956,
  "والد": 957,
  "مرد": 958,
  "مقیم": 959,
  "جولا": 960,
  "وجوہ": 961,
  "چور": 962,
  "فی": 963,
  "حی": 964,
  "تلاش": 965,
  "خال": 966,
  "لاش": 967,
  "بارود": 968,
  "پشاور": 969,
  "انکار": 970,
  "خواتین": 971,
  "بناا": 972,
  "پریس": 973,
  "چھوڑ": 974,
  "باوجود": 975,
  "مسلح": 976,
  "بازو": 977,
  "مطالبہ": 978,
  "چا": 979,
  "شرکت": 980,
  "حیر": 981,
  "ہانگ": 982,
  "کانگ": 983,
  "سپنر": 984,
  "بیٹنگ": 985,
  "پیٹرک": 986,
  "سرجر": 987,
  "وسیع": 988,
  "منصوب": 989,
  "مذاکر": 990,
  "رکھن": 991,
  "ہی تاہم": 992,
  "انٹرنیٹ": 993,
  "مارچ": 994,
  "خلا": 995,
  "کیٹیگر": 996,
  "آسٹرا": 997,
  "رہن": 998,
  "شمال": 999,
  "فٹ": 1000,
  "ٹیلیگرام": 1001,
  "چیمپئنز": 1002,
  "کون": 1003,
  "طاقت": 1004,
  "رد": 1005,
  "افواج": 1006,
  "اوور": 1007,
  "نوعیت": 1008,
  "قسم": 1009,
  "ایشا": 1010,
  "پیشکش": 1011,
  "داعش": 1012,
  "کیا ان": 1013,
  "سیم": 1014,
  "مثبت": 1015,
  "مصنوع": 1016,
  "اخبار": 1017,
  "مریض": 1018,
  "جوہر": 1019,
  "پیمائش": 1020,
  "بگٹ": 1021,
  "بنان": 1022,
  "یافتہ": 1023,
  "دھار": 1024,
  "باصلاحیت": 1025,
  "یادگار": 1026,
  "پرائیویٹ": 1027,
  "سادہ": 1028,
  "ویسٹ": 1029,
  "انڈیز": 1030,
  "دستخط": 1031,
  "رکن": 1032,
  "تجزا": 1033,
  "تباد": 1034,
  "تھی لیکن": 1035,
  "نتیجہ": 1036,
  "مارک": 1037,
  "طرز": 1038,
  "کھینچ": 1039,
  "منفرد": 1040,
  "جذبات": 1041,
  "انسان": 1042,
  "عم": 1043,
  "مسجد": 1044,
  "کعبہ": 1045,
  "گا یہ": 1046,
  "جزیر": 1047,
  "یونیورسٹ": 1048,
  "نفسیات": 1049,
  "حرب": 1050,
  "اگرچہ": 1051,
  "خاموش": 1052,
  "رفت": 1053,
  "عزم": 1054,
  "نیشنل": 1055,
  "انڈونیشا": 1056,
  "فرانسیس": 1057,
  "معاہدہ": 1058,
  "بھرت": 1059,
  "کت": 1060,
  "خط": 1061,
  "برطانو": 1062,
  "وا": 1063,
  "حام": 1064,
  "ووگ": 1065,
  "نکول": 1066,
  "ورژن": 1067,
  "سست": 1068,
  "چیف": 1069,
  "نامناسب": 1070,
  "صفا": 1071,
  "گا تاہم": 1072,
  "واحد": 1073,
  "مجرم": 1074,
  "اڈیالہ": 1075,
  "خرم": 1076,
  "علاج": 1077,
  "الگ": 1078,
  "اندا": 1079,
  "ذمہ": 1080,
  "متعارف": 1081,
  "سسٹم": 1082,
  "ناقابل": 1083,
  "مقتول": 1084,
  "ملزم": 1085,
  "کروز": 1086,
  "تھا ایک": 1087,
  "رحم": 1088,
  "اقتدار": 1089,
  "ون": 1090,
  "سمجھت": 1091,
  "خوبصورت": 1092,
  "لفظ": 1093,
  "سمگلر": 1094,
  "فیکٹر": 1095,
  "سلم": 1096,
  "ٹیسٹ": 1097,
  "پیٹرول": 1098,
  "بیس": 1099,
  "پٹی": 1100,
  "ہا <NUM": 1101,
  "اکتوبر": 1102,
  "ی": 1103,
  "وراٹ": 1104,
  "گرمجوش": 1105,
  "تفتیش": 1106,
  "جمع": 1107,
  "بشر": 1108,
  "حکم": 1109,
  "تعاون": 1110,
  "ایچ": 1111,
  "نسبت": 1112,
  "گاؤں": 1113,
  "گروپ": 1114,
  "امیر": 1115,
  "کریم": 1116,
  "مانت": 1117,
  "مذہب": 1118,
  "مراد": 1119,
  "گا اور": 1120,
  "لبن": 1121,
  "اٹھا": 1122,
  "اہلیہ": 1123,
  "سانس": 1124,
  "سینکڑ": 1125,
  "جعل": 1126,
  "تعمیر": 1127,
  "سکرین": 1128,
  "گول": 1129,
  "ایکٹ": 1130,
  "سائبر": 1131,
  "تاثر": 1132,
  "ہا دوسر": 1133,
  "آنت": 1134,
  "کینسر": 1135,
  "مسافر": 1136,
  "شہزاد": 1137,
  "سٹار": 1138,
  "ڈونلڈ": 1139,
  "ورز": 1140,
  "متعلقہ": 1141,
  "آن": 1142,
  "افسوس": 1143,
  "وثیقہ": 1144,
  "نشانہ": 1145,
  "برتر": 1146,
  "کورٹ": 1147,
  "نیاز": 1148,
  "سن": 1149,
  "جارحیت": 1150,
  "ہا اب": 1151,
  "راؤنڈر": 1152,
  "فوڈ": 1153,
  "رائیڈرز": 1154,
  "تھا بی": 1155,
  "سنا": 1156,
  "انسٹ": 1157,
  "پہن": 1158,
  "تجربہ": 1159,
  "شرط": 1160,
  "تشدد": 1161,
  "فارس": 1162,
  "ہلاکت": 1163,
  "اڑا": 1164,
  "دیوار": 1165,
  "کنگز": 1166,
  "حارث": 1167,
  "رؤف": 1168,
  "فخر": 1169,
  "زم": 1170,
  "اسامہ": 1171,
  "طاہر": 1172,
  "القاعدہ": 1173,
  "پناہ": 1174,
  "غور": 1175,
  "دیکھا": 1176,
  "بہادر": 1177,
  "ریزانگ": 1178,
  "سبھ": 1179,
  "دیر": 1180,
  "لو": 1181,
  "نیا": 1182,
  "دوستانہ": 1183,
  "خوش": 1184,
  "لین": 1185,
  "اپوزیشن": 1186,
  "ثبوت": 1187,
  "شیرپاؤ": 1188,
  "خٹک": 1189,
  "ہدف": 1190,
  "پڑ": 1191,
  "سازش": 1192,
  "متحرک": 1193,
  "ناممکن": 1194,
  "نہیں": 1195,
  "کان": 1196,
  "واٹر": 1197,
  "فائرنگ": 1198,
  "شکست": 1199,
  "کھو": 1200,
  "عجیب": 1201,
  "دروا": 1202,
  "سائز": 1203,
  "سینٹ": 1204,
  "ڈیزائن": 1205,
  "سکتا": 1206,
  "دولت": 1207,
  "مال": 1208,
  "آمدن": 1209,
  "ٹیکس": 1210,
  "تعریف": 1211,
  "گھنٹ": 1212,
  "پرواز": 1213,
  "روم": 1214,
  "پھیل": 1215,
  "احساس": 1216,
  "والدہ": 1217,
  "ساڑھ": 1218,
  "کنٹرول": 1219,
  "فورسز": 1220,
  "ایجنس": 1221,
  "اینڈ": 1222,
  "سہولت": 1223,
  "پرائس": 1224,
  "غیرمل": 1225,
  "انگلینڈ": 1226,
  "سبق": 1227,
  "جتن": 1228,
  "بنت": 1229,
  "آئین": 1230,
  "بلوچ": 1231,
  "اکثریت": 1232,
  "مانن": 1233,
  "خاندان": 1234,
  "گئے": 1235,
  "توقع": 1236,
  "لحاظ": 1237,
  "خیز": 1238,
  "الدین": 1239,
  "ماحول": 1240,
  "ہی یوکرین": 1241,
  "حیدرآباد": 1242,
  "آوٹ": 1243,
  "گرا": 1244,
  "اوورز": 1245,
  "ایونٹ": 1246,
  "پار": 1247,
  "مہین": 1248,
  "گیا اس": 1249,
  "ورٹیگو": 1250,
  "کپڑ": 1251,
  "شعب": 1252,
  "گارمنٹس": 1253,
  "روملر": 1254,
  "حیدر": 1255,
  "برآمد": 1256,
  "سلامت": 1257,
  "کمیٹ": 1258,
  "میچز": 1259,
  "مقابل": 1260,
  "تھی اب": 1261,
  "دہا": 1262,
  "پہیہ": 1263,
  "جام": 1264,
  "فہرست": 1265,
  "ہا ہم": 1266,
  "میگزین": 1267,
  "مہارت": 1268,
  "ادائا": 1269,
  "قبضہ": 1270,
  "تب": 1271,
  "فضائیہ": 1272,
  "نوٹ": 1273,
  "آدم": 1274,
  "پاتھک": 1275,
  "جرمن": 1276,
  "جانن": 1277,
  "نصف": 1278,
  "پراسرار": 1279,
  "سڑک": 1280,
  "ٹویٹس": 1281,
  "بیان": 1282,
  "ذہانت": 1283,
  "گا لیکن": 1284,
  "پتن": 1285,
  "تھی یہ": 1286,
  "گولڈ": 1287,
  "سلور": 1288,
  "نواز": 1289,
  "ہو وہ": 1290,
  "فنڈ": 1291,
  "کلبز": 1292,
  "قوت": 1293,
  "پلیٹینم": 1294,
  "ایمرجنگ": 1295,
  "ریلیز": 1296,
  "اہمیت": 1297,
  "بک": 1298,
  "پبلک": 1299,
  "نقصان": 1300,
  "مستقل": 1301,
  "سربجیت": 1302,
  "متنازع": 1303,
  "پوائنٹس": 1304,
  "گزرت": 1305,
  "مسلمان": 1306,
  "چمک": 1307,
  "سکی": 1308,
  "سوٹ": 1309,
  "شواہد": 1310,
  "پیڈ": 1311,
  "مارٹم": 1312,
  "ٹانگ": 1313,
  "لباس": 1314,
  "میں": 1315,
  "چٹاگانگ": 1316,
  "میجر": 1317,
  "عبدالستار": 1318,
  "تعزیت": 1319,
  "ڈھاکہ": 1320,
  "ٹیسٹنگ": 1321,
  "سپیڈ": 1322,
  "ہا نیوز": 1323,
  "کیا سب": 1324,
  "دہ": 1325,
  "لمح": 1326,
  "یادو": 1327,
  "مقدمہ": 1328,
  "انحصار": 1329,
  "مفاد": 1330,
  "لاگو": 1331,
  "اٹھان": 1332,
  "ٹورنامنٹس": 1333,
  "شرائط": 1334,
  "کرے": 1335,
  "باقاعد": 1336,
  "رابط": 1337,
  "دکان": 1338,
  "ڈیرل": 1339,
  "چیپمین": 1340,
  "گہرا": 1341,
  "ویر": 1342,
  "چکر": 1343,
  "تھا اب": 1344,
  "فائلز": 1345,
  "مندر": 1346,
  "اکی": 1347,
  "مدت": 1348,
  "شر": 1349,
  "تحقیقات": 1350,
  "کرائم": 1351,
  "سین": 1352,
  "دہراا": 1353,
  "اعتراف": 1354,
  "گل": 1355,
  "پیشہ": 1356,
  "جرائم": 1357,
  "سازوسام": 1358,
  "وعد": 1359,
  "فلورنس": 1360,
  "پارل": 1361,
  "ایو": 1362,
  "ایشن": 1363,
  "وعدہ": 1364,
  "پولین": 1365,
  "غصا": 1366,
  "خوفزدہ": 1367,
  "لطیف": 1368,
  "بھیجت": 1369,
  "گیٹ": 1370,
  "پورٹ": 1371,
  "ہا اگر": 1372,
  "بروکلن": 1373,
  "پیج": 1374,
  "امو": 1375,
  "ہی ایف": 1376,
  "فیک": 1377,
  "خاتمہ": 1378,
  "فضل": 1379,
  "ٹرین": 1380,
  "بو": 1381,
  "مناسب": 1382,
  "سٹاف": 1383,
  "شرم": 1384,
  "مود": 1385,
  "ازا": 1386,
  "ریٹین": 1387,
  "مرز": 1388,
  "صاحب": 1389,
  "آنکھ": 1390,
  "باقاعدہ": 1391,
  "ہا ڈاکٹر": 1392,
  "برعکس": 1393,
  "بوجھ": 1394,
  "محتاط": 1395,
  "جسم": 1396,
  "گھڑ": 1397,
  "لائٹ": 1398,
  "سورج": 1399,
  "گھریلو": 1400,
  "ضمانت": 1401,
  "نشر": 1402,
  "سچی": 1403,
  "سچا": 1404,
  "جھوٹ": 1405,
  "اعتراض": 1406,
  "قوانین": 1407,
  "دلوا": 1408,
  "فیمل": 1409,
  "اقبال": 1410,
  "سکا ،تصویر": 1411,
  "گا یاد": 1412,
  "بشمول": 1413,
  "آم": 1414,
  "مین": 1415,
  "بیانا": 1416,
  "تناؤ": 1417,
  "ناقدین": 1418,
  "تھی انھ": 1419,
  "یونٹس": 1420,
  "سٹیج": 1421,
  "ہپ": 1422,
  "ہاپ": 1423,
  "فلپراچ": 1424,
  "درد": 1425,
  "چل": 1426,
  "چھپا": 1427,
  "جم": 1428,
  "حرکت": 1429,
  "قابلیت": 1430,
  "ڈن": 1431,
  "تھی ان": 1432,
  "نیٹ": 1433,
  "ورک": 1434,
  "آغا": 1435,
  "قاتلانہ": 1436,
  "زب": 1437,
  "گیا اسلام": 1438,
  "کنونشن": 1439,
  "خطاب": 1440,
  "مشرف": 1441,
  "روانہ": 1442,
  "قافلہ": 1443,
  "سخت مشرف": 1444,
  "پل": 1445,
  "وارد": 1446,
  "مرمت": 1447,
  "تھا دائی": 1448,
  "پمپ": 1449,
  "حکمران": 1450,
  "دستبردار": 1451,
  "اتھارٹ": 1452,
  "بیٹھ": 1453,
  "نیت": 1454,
  "شردھ": 1455,
  "حجام": 1456,
  "لای": 1457,
  "لاعلم": 1458,
  "دیا ان": 1459,
  "محمود": 1460,
  "سندھو": 1461,
  "استغاثہ": 1462,
  "مانگ": 1463,
  "تیسر": 1464,
  "معائنہ": 1465,
  "سٹریٹیجک": 1466,
  "رفعت": 1467,
  "بندوبست": 1468,
  "ہا ممکنہ": 1469,
  "ہیز": 1470,
  "لینس": 1471,
  "لقب": 1472,
  "ہا امرا": 1473,
  "تہہ": 1474,
  "چڑھ": 1475,
  "بھال": 1476,
  "سالانہ": 1477,
  "اقتصاد": 1478,
  "ڈالرز": 1479,
  "کما": 1480,
  "فیلو": 1481,
  "یہود": 1482,
  "مصر": 1483,
  "حزب": 1484,
  "مزاحمت": 1485,
  "حوث": 1486,
  "باغ": 1487,
  "ہی لیکن": 1488,
  "صوف": 1489,
  "ہوش": 1490,
  "منٹ": 1491,
  "ہار": 1492,
  "امداد": 1493,
  "مر": 1494,
  "جج": 1495,
  "دھر": 1496,
  "عزت": 1497,
  "حسب": 1498,
  "معزز آپ": 1499,
  "بھ": 1500,
  "بھسم": 1501,
  "خنجر": 1502,
  "ناقص": 1503,
  "تھام": 1504,
  "الیکٹرانک": 1505,
  "رس": 1506,
  "پیچھ": 1507,
  "ہا ایک": 1508,
  "خفیہ": 1509,
  "سیکس": 1510,
  "مشہور": 1511,
  "جیکسن": 1512,
  "کلنٹن": 1513,
  "ہدایت": 1514,
  "مجاز": 1515,
  "گی اس": 1516,
  "شکوہ": 1517,
  "توسیع": 1518,
  "بنات": 1519,
  "سلس": 1520,
  "لیبا": 1521,
  "ساختہ": 1522,
  "پرا": 1523,
  "کسوہ": 1524,
  "مصنف": 1525,
  "مواقع": 1526,
  "بڑھا": 1527,
  "درواز": 1528,
  "ترجیح": 1529,
  "ڈائریکٹر": 1530,
  "ایجنٹ": 1531,
  "گینگ": 1532,
  "ولیم": 1533,
  "بھرپور": 1534,
  "نمٹ": 1535,
  "وثیق": 1536,
  "ویز": 1537,
  "لنک": 1538,
  "خصوصا": 1539,
  "آفریدی": 1540,
  "زمبابو": 1541,
  "ہا فرنچائز": 1542,
  "بینا": 1543,
  "صاف": 1544,
  "ڈیوٹ": 1545,
  "کھ": 1546,
  "سکا سب": 1547,
  "سٹیشنز": 1548,
  "رہا ان": 1549,
  "توجہ": 1550,
  "قمر": 1551,
  "شو": 1552,
  "کوتاہ": 1553,
  "ہوئی": 1554,
  "گا بنگلہ": 1555,
  "خدش": 1556,
  "ہیگ": 1557,
  "زما": 1558,
  "اجتماع": 1559,
  "فساد": 1560,
  "اڈ": 1561,
  "گراا": 1562,
  "نیٹو": 1563,
  "سنگین": 1564,
  "ہوئے": 1565,
  "ماس": 1566,
  "زور": 1567,
  "براڈ": 1568,
  "ڈائریکٹ": 1569,
  "سائننگ": 1570,
  "دیرینہ": 1571,
  "ارک": 1572,
  "آصف": 1573,
  "ضد": 1574,
  "گھران": 1575,
  "دھرمیندر": 1576,
  "سراہت": 1577,
  "ہا آپ": 1578,
  "ٹن": 1579,
  "وزن": 1580,
  "نشا": 1581,
  "ٹائمز": 1582,
  "ٹو": 1583,
  "مہی": 1584,
  "طلب": 1585,
  "پاور": 1586,
  "ہوا ای": 1587,
  "تفریح": 1588,
  "کراا": 1589,
  "بائیکاٹ": 1590,
  "حکمت": 1591,
  "قید": 1592,
  "سلسلہ": 1593,
  "چرچ": 1594,
  "ہی عمر": 1595,
  "داخلہ": 1596,
  "عدن": 1597,
  "صدیق": 1598,
  "کرنس": 1599,
  "وون": 1600,
  "نقد": 1601,
  "آرہا": 1602,
  "ٹکٹس": 1603,
  "ہی دون": 1604,
  "مشاورت": 1605,
  "پرس": 1606,
  "بڑھاا": 1607,
  "گھوم": 1608,
  "سائیکل": 1609,
  "ہینڈل": 1610,
  "پھنس": 1611,
  "ہا کچھ": 1612,
  "طرفہ": 1613,
  "مثال": 1614,
  "متنازعہ": 1615,
  "فاؤنڈیشن": 1616,
  "تاحال": 1617,
  "تھا اگرچہ": 1618,
  "داس": 1619,
  "مذاق": 1620,
  "کرد": 1621,
  "تھی وہ": 1622,
  "جادوگر": 1623,
  "بغاوت": 1624,
  "دھماک": 1625,
  "الٹ": 1626,
  "رسوخ": 1627,
  "عموم": 1628,
  "پارٹ": 1629,
  "فائل": 1630,
  "بھانت": 1631,
  "آنسو": 1632,
  "گیس": 1633,
  "اعتماد": 1634,
  "ہا گذشتہ": 1635,
  "یوٹیوب": 1636,
  "یونٹ": 1637,
  "کوم": 1638,
  "متاثرہ": 1639,
  "خوفناک": 1640,
  "کھول": 1641,
  "طریقہ": 1642,
  "مراحل": 1643,
  "اعلان": 1644,
  "سرخ": 1645,
  "رہا ایر": 1646,
  "ذخائر": 1647,
  "بدانتظامی": 1648,
  "اعلاما": 1649,
  "ریاست": 1650,
  "دارالحکومت": 1651,
  "ابراہیم": 1652,
  "ٹیل": 1653,
  "تھا پاکست": 1654,
  "سیکٹر": 1655,
  "موڑ": 1656,
  "ہی میر": 1657,
  "نوئیڈ": 1658,
  "ہند": 1659,
  "نیپال": 1660,
  "جانچ": 1661,
  "پڑتال": 1662,
  "حل": 1663,
  "فرار": 1664,
  "ڈیجیٹل": 1665,
  "جوش": 1666,
  "موضوع": 1667,
  "بیلسٹک": 1668,
  "بلند": 1669,
  "عظیم": 1670,
  "صحر": 1671,
  "بحیرہ": 1672,
  "فر": 1673,
  "بالآخر": 1674,
  "فیصل": 1675,
  "شفقت": 1676,
  "مجید": 1677,
  "انٹیلیجنس": 1678,
  "ونگ": 1679,
  "شرمندہ": 1680,
  "بالکل": 1681,
  "سیف": 1682,
  "گا حال": 1683,
  "گا بہن": 1684,
  "پاؤ": 1685,
  "شہادت": 1686,
  "فائیو": 1687,
  "موبائل": 1688,
  "ہینڈ": 1689,
  "سروس": 1690,
  "پندرہ": 1691,
  "ردعمل": 1692,
  "کمیشن": 1693,
  "لیس": 1694,
  "جونیئر": 1695,
  "پھینک": 1696,
  "سم": 1697,
  "ماریہ": 1698,
  "دھیر": 1699,
  "کال": 1700,
  "نگار": 1701,
  "بلوچست": 1702,
  "طیارہ": 1703,
  "ذرائع": 1704,
  "ہا جب": 1705,
  "مقرر": 1706,
  "آپریشنل": 1707,
  "چاہا اس": 1708,
  "کلپ": 1709,
  "فوٹیج": 1710,
  "ڈر": 1711,
  "صنعت": 1712,
  "بیٹریس": 1713,
  "بہن": 1714,
  "فرم": 1715,
  "جانبدار": 1716,
  "دکھ": 1717,
  "پیما": 1718,
  "آخرکار": 1719,
  "ہلاک": 1720,
  "باشند": 1721,
  "لیے": 1722,
  "مینز": 1723,
  "حیرت": 1724,
  "مبتل": 1725,
  "طبق": 1726,
  "نذر": 1727,
  "نتائج": 1728,
  "تربیت": 1729,
  "کوچ": 1730,
  "بھار": 1731,
  "پہنچاا": 1732,
  "قبر": 1733,
  "سماج": 1734,
  "آئے": 1735,
  "یکا": 1736,
  "مخالف": 1737,
  "گھومت": 1738,
  "الحق": 1739,
  "وحید": 1740,
  "ہارون": 1741,
  "صلاح": 1742,
  "عادل": 1743,
  "خبردار": 1744,
  "کلرک": 1745,
  "رویندر": 1746,
  "کوشک": 1747,
  "نبی": 1748,
  "شاکر": 1749,
  "ٹیک": 1750,
  "نیکسٹ": 1751,
  "تھا یہ": 1752,
  "گیا ،تصویر": 1753,
  "رن": 1754,
  "کھیلت": 1755,
  "سیکریٹر": 1756,
  "وکرم": 1757,
  "مسر": 1758,
  "صحیح": 1759,
  "واشنگٹن": 1760,
  "مغرب": 1761,
  "مایوس": 1762,
  "فرض": 1763,
  "قدرت": 1764,
  "ماہرین": 1765,
  "فیشن": 1766,
  "موسم": 1767,
  "سرن": 1768,
  "خودکش": 1769,
  "شہزادہ": 1770,
  "اینڈریو": 1771,
  "ملازم": 1772,
  "حقائق": 1773,
  "گریز": 1774,
  "موازنہ": 1775,
  "ٹکر": 1776,
  "رسل": 1777,
  "نقل": 1778,
  "اللب": 1779,
  "خراس": 1780,
  "انجیکشن": 1781,
  "خوشدل": 1782,
  "سعد": 1783,
  "بیگ": 1784,
  "عباس": 1785,
  "حریف": 1786,
  "خوشگوار": 1787,
  "بری": 1788,
  "نوا": 1789,
  "شٹر": 1790,
  "ڈاؤن": 1791,
  "تھی سنہ": 1792,
  "سیریز": 1793,
  "چیمپیئنز": 1794,
  "تھا لڑ": 1795,
  "نافذ": 1796,
  "بردار": 1797,
  "اندھیر": 1798,
  "پکار": 1799,
  "چوک": 1800,
  "دکھاا": 1801,
  "دفتر": 1802,
  "حیثیت": 1803,
  "شمولیت": 1804,
  "زبان": 1805,
  "کرکٹرز": 1806,
  "فائنل": 1807,
  "ٹائٹل": 1808,
  "چھٹکار": 1809,
  "رسا": 1810,
  "کھی": 1811,
  "پڑی": 1812,
  "پچھل": 1813,
  "لائیو": 1814,
  "فیس": 1815,
  "ہوٹل": 1816,
  "نفرت": 1817,
  "کابل": 1818,
  "یوسفز": 1819,
  "پروفیسر": 1820,
  "سریپرن": 1821,
  "پچھ": 1822,
  "درحقیقت": 1823,
  "اڈا": 1824,
  "نیچ": 1825,
  "کھٹمنڈو": 1826,
  "کیا سیم": 1827,
  "ہندو": 1828,
  "ڈس": 1829,
  "نظریہ": 1830,
  "بچپن": 1831,
  "طلبہ": 1832,
  "کومیک": 1833,
  "روڈ": 1834,
  "ٹرانسپورٹ": 1835,
  "کارپوریشن": 1836,
  "پرساد": 1837,
  "آودھا": 1838,
  "انسداد": 1839,
  "شوق": 1840,
  "راشد": 1841,
  "دیکھن": 1842,
  "بیانیہ": 1843,
  "سنبھال": 1844,
  "گا ،تصویر": 1845,
  "مائیکل": 1846,
  "قلندرز": 1847,
  "گلیڈ": 1848,
  "ایٹرز": 1849,
  "کلومیٹر": 1850,
  "شاٹ": 1851,
  "ٹیوٹ": 1852,
  "فار": 1853,
  "مالک": 1854,
  "اتفاق": 1855,
  "تعلیم": 1856,
  "انویسٹمنٹ": 1857,
  "النصر": 1858,
  "الہلال": 1859,
  "الاهل": 1860,
  "الاتحاد": 1861,
  "انگلش": 1862,
  "گالف": 1863,
  "ذوالفقار": 1864,
  "دبا": 1865,
  "مداخلت": 1866,
  "ہا ٹورنامنٹ": 1867,
  "ڈائمنڈ": 1868,
  "نشاندہ": 1869,
  "ہا احمد": 1870,
  "گا می": 1871,
  "ملی": 1872,
  "اونٹ": 1873,
  "قبائل": 1874,
  "تھوڑ": 1875,
  "ہڈی": 1876,
  "آرام": 1877,
  "سیکھ": 1878,
  "سونک": 1879,
  "فصل": 1880,
  "ریال": 1881,
  "مجموع": 1882,
  "قلندر": 1883,
  "بجٹ": 1884,
  "خراب": 1885,
  "سبب": 1886,
  "قابو": 1887,
  "محفوظ": 1888,
  "اہل": 1889,
  "برقع": 1890,
  "تھان": 1891,
  "کرواا": 1892,
  "پاش": 1893,
  "ناصر": 1894,
  "مشق": 1895,
  "چیئرمین": 1896,
  "ضبط": 1897,
  "خطرناک": 1898,
  "سیگل": 1899,
  "ہفنگٹن": 1900,
  "رعایت": 1901,
  "اردن": 1902,
  "لگات": 1903,
  "نصير": 1904,
  "مام": 1905,
  "پھوپھ": 1906,
  "لنکن": 1907,
  "چیئرپرسن": 1908,
  "تشویش": 1909,
  "بھگ": 1910,
  "مدر": 1911,
  "انجو": 1912,
  "وفادار": 1913,
  "کھوج": 1914,
  "بلاا": 1915,
  "نزدیک": 1916,
  "مترادف": 1917,
  "وزیراعظم": 1918,
  "گیم": 1919,
  "شکاا": 1920,
  "معالج": 1921,
  "کپیسٹ": 1922,
  "کل": 1923,
  "ہیریسن": 1924,
  "شراب": 1925,
  "تاجر": 1926,
  "جمپرز": 1927,
  "اینٹ": 1928,
  "سٹالینز": 1929,
  "پری": 1930,
  "مہنگا": 1931,
  "لوکم": 1932,
  "مادھور": 1933,
  "دائی": 1934,
  "صدی": 1935,
  "آسام": 1936,
  "کاپ": 1937,
  "ٹنکوف": 1938,
  "بیلنس": 1939,
  "سائنس": 1940,
  "اجلال": 1941,
  "تم": 1942,
  "ایئرپورٹ": 1943,
  "انجینئرز": 1944,
  "قاف": 1945,
  "بشیر": 1946,
  "زیب": 1947,
  "بیریزوس": 1948,
  "ویلنٹینو": 1949,
  "چھاؤن": 1950,
  "ابوالمنظور": 1951,
  "دینک": 1952,
  "سمواد": 1953,
  "جسٹس": 1954,
  "کابینہ": 1955,
  "اجلاس": 1956,
  "گا اسی": 1957,
  "لمز": 1958,
  "فیسیلیٹ": 1959,
  "آفیشل": 1960,
  "سکت انھ": 1961,
  "انفراریڈ": 1962,
  "کیمرے": 1963,
  "فریم": 1964,
  "ریٹ": 1965,
  "ہا آا": 1966,
  "فنکار": 1967,
  "ات": 1968,
  "مرح": 1969,
  "مسکراہٹیں": 1970,
  "قہق": 1971,
  "ہی آج": 1972,
  "ہا عدالت": 1973,
  "راجپال": 1974,
  "اتا": 1975,
  "لپت": 1976,
  "ہا سنہ": 1977,
  "مرل": 1978,
  "پروجیکٹس": 1979,
  "لمیٹڈ": 1980,
  "تھی عدالت": 1981,
  "باکس": 1982,
  "آفس": 1983,
  "گا ایس": 1984,
  "گی سومین": 1985,
  "سمت": 1986,
  "سٹریٹجک": 1987,
  "ہوگا تاہم": 1988,
  "زمبابوے": 1989,
  "بورڈز": 1990,
  "گا کسی": 1991,
  "میمبرز": 1992,
  "پارٹیسپیشن": 1993,
  "ایگریمنٹ": 1994,
  "تھا ای": 1995,
  "منصوبوں": 1996,
  "آئیڈیاز": 1997,
  "دھاندل": 1998,
  "نشست": 1999,
  "مینڈیٹ": 2000,
  "چھین": 2001,
  "اتوار": 2002,
  "مناسبت": 2003,
  "ہی پی": 2004,
  "سنیم": 2005,
  "لات": 2006,
  "ہا سینیئر": 2007,
  "پنکج": 2008,
  "انسانیت": 2009,
  "کرا راز": 2010,
  "اکیس": 2011,
  "فل": 2012,
  "حب": 2013,
  "الوطن": 2014,
  "جوڑت": 2015,
  "ہی اکیس": 2016,
  "ارون": 2017,
  "کھیترپال": 2018,
  "اعزاز": 2019,
  "پرم": 2020,
  "مرگ": 2021,
  "گیا فلم": 2022,
  "پراپرٹ": 2023,
  "عمارت": 2024,
  "ڈھل": 2025,
  "صلاحت": 2026,
  "ہی نیدرلینڈز": 2027,
  "روٹرڈیم": 2028,
  "ایراسمس": 2029,
  "محقق": 2030,
  "مولڈائیک": 2031,
  "مطالع": 2032,
  "تھی نتائج": 2033,
  "سٹی": 2034,
  "لیا سٹی": 2035,
  "سردارغیاث": 2036,
  "ور": 2037,
  "سابقہ": 2038,
  "مجرمانہ": 2039,
  "نیویگیشن": 2040,
  "ہی آسم": 2041,
  "پلیٹنچک": 2042,
  "آمد": 2043,
  "سش": 2044,
  "قبول": 2045,
  "گیا بی": 2046,
  "انڈونیشین": 2047,
  "تکمیل": 2048,
  "ہا رفال": 2049,
  "جکارتہ": 2050,
  "ڈاسو": 2051,
  "شہریت": 2052,
  "تھی اپن": 2053,
  "رہا انھ": 2054,
  "وائس": 2055,
  "نوٹس": 2056,
  "جھان": 2057,
  "تھا عمر": 2058,
  "پرست": 2059,
  "ہی ایپسٹین": 2060,
  "کتابت": 2061,
  "لابنگ": 2062,
  "کیا ایپسٹین": 2063,
  "دان": 2064,
  "لارڈ": 2065,
  "مینڈیلسن": 2066,
  "مؤقف": 2067,
  "پرسکون": 2068,
  "سرا": 2069,
  "ہا اہم": 2070,
  "ہو ہم": 2071,
  "عملدرآمد": 2072,
  "گا پاکست": 2073,
  "ن": 2074,
  "اسمبل": 2075,
  "وہپ": 2076,
  "چوہدر": 2077,
  "ہا ہر": 2078,
  "تھا انتہا": 2079,
  "تھا ما": 2080,
  "تھی جہ": 2081,
  "تھی جس": 2082,
  "ریسکیو": 2083,
  "گزارش": 2084,
  "جائی ان": 2085,
  "پروفیشنل": 2086,
  "لائف": 2087,
  "ہا وزیر": 2088,
  "متن": 2089,
  "بکواس": 2090,
  "نہی ،تصویر": 2091,
  "سنیچر": 2092,
  "کانگریس": 2093,
  "حمید": 2094,
  "سرجن": 2095,
  "ویٹرو": 2096,
  "معائ": 2097,
  "تھیٹر": 2098,
  "ہا آر": 2099,
  "ٹریننگ": 2100,
  "سیشن": 2101,
  "ہی پاکست": 2102,
  "حیاتیات": 2103,
  "سرکیڈین": 2104,
  "ردھم": 2105,
  "کیمیا": 2106,
  "ماد": 2107,
  "بگڑ": 2108,
  "ہی اسی": 2109,
  "تھراپ": 2110,
  "لیمپ": 2111,
  "سکا تاہم": 2112,
  "ایڈجسٹ": 2113,
  "گی بابر": 2114,
  "کر عافیہ": 2115,
  "ارتکاب": 2116,
  "ہا وکیل": 2117,
  "ضابطہ": 2118,
  "متعین": 2119,
  "کونس": 2120,
  "جھوٹ محض": 2121,
  "صوابدید": 2122,
  "انفارمیشن": 2123,
  "گا وکیل": 2124,
  "اٹھات": 2125,
  "فوجدار": 2126,
  "شاہد": 2127,
  "کمبوہ": 2128,
  "ایڈووکیٹ": 2129,
  "عمد": 2130,
  "ٹرائل": 2131,
  "خطا": 2132,
  "صلح": 2133,
  "ہا جاوید": 2134,
  "پیداوار": 2135,
  "فلیمنگو": 2136,
  "نان": 2137,
  "تعینات": 2138,
  "رجسٹر": 2139,
  "سفارتکار": 2140,
  "عملہ": 2141,
  "اہلخانہ": 2142,
  "بیوی": 2143,
  "افغانستان": 2144,
  "سوڈ": 2145,
  "سلام": 2146,
  "کیا پاکست": 2147,
  "سپرٹ": 2148,
  "چھاپ": 2149,
  "ہا کرکٹ": 2150,
  "رہا سب": 2151,
  "ہوگا انتخاب": 2152,
  "جمہور": 2153,
  "اصلاح": 2154,
  "ہا عوام": 2155,
  "تقاریر": 2156,
  "جائی عبور": 2157,
  "ہا گراس": 2158,
  "میٹرنگ": 2159,
  "حساب": 2160,
  "ایکسپورٹ": 2161,
  "ہا نیپر": 2162,
  "مجو": 2163,
  "ریگولیشنز": 2164,
  "نفی": 2165,
  "قحط": 2166,
  "نظرانداز": 2167,
  "کیا آا": 2168,
  "ہی اسرائیل": 2169,
  "گم": 2170,
  "ملا صحاف": 2171,
  "فیض": 2172,
  "لاکھان": 2173,
  "شکریہ": 2174,
  "حسام": 2175,
  "عاصم": 2176,
  "موسیق": 2177,
  "ہی فلپراچ": 2178,
  "نمبر": 2179,
  "شکریہ لو": 2180,
  "انڈا موسیق": 2181,
  "لاسٹ": 2182,
  "گان": 2183,
  "تھا ویب": 2184,
  "اپناا": 2185,
  "تھا راکیل": 2186,
  "شخصیت": 2187,
  "یوگا": 2188,
  "گیا برٹش": 2189,
  "ایسوس": 2190,
  "ایسیتھٹک": 2191,
  "پلاسٹک": 2192,
  "سرجنز": 2193,
  "نیوجنٹ": 2194,
  "بدقسمت": 2195,
  "انڈسٹر": 2196,
  "فرقہ": 2197,
  "تنوع": 2198,
  "سمجھن": 2199,
  "مظاہرہ": 2200,
  "ڈنکر": 2201,
  "کہلات": 2202,
  "ہی تر": 2203,
  "یون": 2204,
  "بذریعہ": 2205,
  "بنا انسان": 2206,
  "ہی حسن": 2207,
  "زید": 2208,
  "ہا کولمبو": 2209,
  "اٹھاا": 2210,
  "آہن": 2211,
  "ہولناک": 2212,
  "تسلسل": 2213,
  "ہا نقاب": 2214,
  "رہی میر": 2215,
  "کی پہ": 2216,
  "گیا پھر": 2217,
  "ساجو": 2218,
  "غیرمنطق": 2219,
  "سنات": 2220,
  "رہا راشد": 2221,
  "پراسیکیوٹر": 2222,
  "ظہیر": 2223,
  "وکل": 2224,
  "معالجین": 2225,
  "دی انھ": 2226,
  "دیا بعد": 2227,
  "شراکت": 2228,
  "آیا پرابووو": 2229,
  "ملاقات": 2230,
  "کی ،تصویر": 2231,
  "کیا پہل": 2232,
  "ہوئا تقریب": 2233,
  "جون": 2234,
  "جملہ": 2235,
  "بھارت": 2236,
  "کرکٹر": 2237,
  "ہی ایس": 2238,
  "ربر": 2239,
  "ہو اب": 2240,
  "ہ میر": 2241,
  "گیا ان": 2242,
  "خدا": 2243,
  "سلوک": 2244,
  "تھی کنچن": 2245,
  "مات": 2246,
  "سیلف": 2247,
  "ہیلپ": 2248,
  "آنگن": 2249,
  "واڑ": 2250,
  "منتظم": 2251,
  "روزمرہ": 2252,
  "پکانا": 2253,
  "پلان": 2254,
  "دریغ": 2255,
  "اخراج": 2256,
  "حوصلہ": 2257,
  "افزا": 2258,
  "کی یہ": 2259,
  "تھا فوربز": 2260,
  "ایٹ": 2261,
  "افسانو": 2262,
  "قدیم": 2263,
  "سلطنت": 2264,
  "عثمانیہ": 2265,
  "بنی": 2266,
  "بلیسٹک": 2267,
  "بشار": 2268,
  "الاسد": 2269,
  "ہا یمن": 2270,
  "جر": 2271,
  "مندانہ": 2272,
  "پڑا وہ": 2273,
  "چپس": 2274,
  "کھا": 2275,
  "پڑا ایک": 2276,
  "جینیات": 2277,
  "اعتبار": 2278,
  "مردہ": 2279,
  "رہا لیکن": 2280,
  "ہمت": 2281,
  "رہی پیٹرک": 2282,
  "دوڑ طبی": 2283,
  "مرض اور": 2284,
  "دی ہو": 2285,
  "کام جج": 2286,
  "سکھ": 2287,
  "ورث": 2288,
  "راض": 2289,
  "کمپیوٹرز": 2290,
  "سمارٹ": 2291,
  "فونز": 2292,
  "ٹمٹمات": 2293,
  "فیڈز": 2294,
  "سکرول": 2295,
  "تصادم": 2296,
  "کرائمز": 2297,
  "تلوار": 2298,
  "ابھر": 2299,
  "کی آا": 2300,
  "پھیپھڑ": 2301,
  "پخا": 2302,
  "رنگت": 2303,
  "ریکٹل": 2304,
  "ہا اینڈومیٹریئم": 2305,
  "یوٹرس": 2306,
  "سروائیکل": 2307,
  "اندام": 2308,
  "نہان": 2309,
  "ہا پیشاب": 2310,
  "مثا": 2311,
  "ہا خواتین": 2312,
  "نپل": 2313,
  "رسن": 2314,
  "ہا بہت": 2315,
  "ویران": 2316,
  "تھا سب": 2317,
  "عزیر": 2318,
  "تارا": 2319,
  "جیفر": 2320,
  "ڈسٹربنگ": 2321,
  "کہان کم": 2322,
  "لڑکیوں": 2323,
  "پارٹیز": 2324,
  "کہان کا": 2325,
  "ہا برطانیہ": 2326,
  "اینڈرو": 2327,
  "پاپ": 2328,
  "مائکل": 2329,
  "بھی پچھ": 2330,
  "حقوق": 2331,
  "گی بل": 2332,
  "تادیب": 2333,
  "سیکشن": 2334,
  "پھیلا": 2335,
  "ہ عمر": 2336,
  "فیاض": 2337,
  "ہمراہ": 2338,
  "ہی شکوہ": 2339,
  "ٹرسٹ": 2340,
  "ستر": 2341,
  "لینا": 2342,
  "خرچ": 2343,
  "تھا جب": 2344,
  "جمہوریہ": 2345,
  "رہبر": 2346,
  "روح": 2347,
  "خمین": 2348,
  "دی اسی": 2349,
  "تہران": 2350,
  "پاسدر": 2351,
  "انقلاب": 2352,
  "کمانڈ": 2353,
  "گیا ایر": 2354,
  "سکڈ": 2355,
  "نہی بی": 2356,
  "اشاعت": 2357,
  "موصول": 2358,
  "ہوا امور": 2359,
  "حج": 2360,
  "الحلاب": 2361,
  "نوشتہ": 2362,
  "بیلٹ": 2363,
  "سماد": 2364,
  "رائل": 2365,
  "معاونت": 2366,
  "ایکویٹ": 2367,
  "جا ڈاکٹر": 2368,
  "لان": 2369,
  "گا اونٹ": 2370,
  "کر وہ": 2371,
  "متوجہ": 2372,
  "لیگز": 2373,
  "کر انھ": 2374,
  "حنا": 2375,
  "سمجھا": 2376,
  "کونسلر": 2377,
  "فکرمند": 2378,
  "سیلیبز": 2379,
  "گو": 2380,
  "ایکسپرٹ": 2381,
  "قرارداد": 2382,
  "ہی شاہد": 2383,
  "ہا می": 2384,
  "ہ ہم": 2385,
  "دلائل": 2386,
  "فارمیشن": 2387,
  "ویکس": 2388,
  "سیز": 2389,
  "کاکپٹ": 2390,
  "ایروگنامکس": 2391,
  "ایز": 2392,
  "فلائنگ": 2393,
  "پائلٹ": 2394,
  "کاک": 2395,
  "پٹ": 2396,
  "ہا رپورٹ": 2397,
  "بر": 2398,
  "تھا ملاق": 2399,
  "انکھ": 2400,
  "ٹشو": 2401,
  "رہا رپورٹ": 2402,
  "سپرنٹنڈنٹ": 2403,
  "صفدر": 2404,
  "پمز": 2405,
  "عارف": 2406,
  "بیٹھ ،تصویر": 2407,
  "ٹپ": 2408,
  "دراصل": 2409,
  "سٹیشن": 2410,
  "خوابیدہ": 2411,
  "ناول": 2412,
  "تھی انیس": 2413,
  "جہاد": 2414,
  "تشریح": 2415,
  "استحصال": 2416,
  "جا اپ": 2417,
  "گرام": 2418,
  "صبا": 2419,
  "ڈرام": 2420,
  "شوٹنگ": 2421,
  "یونیفارم": 2422,
  "تھی صبا": 2423,
  "آپریشنز": 2424,
  "سرزد": 2425,
  "مان خیال": 2426,
  "تھا ندا": 2427,
  "چناؤ": 2428,
  "کولکتہ": 2429,
  "نائٹ": 2430,
  "الرحمن": 2431,
  "نیوٹرل": 2432,
  "وینیو": 2433,
  "سکاٹ": 2434,
  "ٹورنامنٹ": 2435,
  "بناا بی": 2436,
  "ایا پیام": 2437,
  "اخو": 2438,
  "کینیڈین": 2439,
  "کرمنل": 2440,
  "ہی ایران": 2441,
  "پڑا نیٹو": 2442,
  "گیا جو": 2443,
  "گا یوکرین": 2444,
  "حدود": 2445,
  "تھا اور": 2446,
  "کیٹج": 2447,
  "بیگو": 2448,
  "چیٹھم": 2449,
  "ہاوس": 2450,
  "تھنک": 2451,
  "ٹینک": 2452,
  "سینئر": 2453,
  "أفغانست": 2454,
  "کارٹر": 2455,
  "ویتنام": 2456,
  "جا درحقیقت": 2457,
  "اینوپ": 2458,
  "پال": 2459,
  "کاسٹنگ": 2460,
  "رائٹس": 2461,
  "سٹالیئنز": 2462,
  "طریقۂ": 2463,
  "ہا ادھر": 2464,
  "بولرمستفیض": 2465,
  "تھا نیلام": 2466,
  "عبید": 2467,
  "داسون": 2468,
  "شناکا": 2469,
  "پرویز": 2470,
  "ایمون": 2471,
  "طلعت": 2472,
  "طیب": 2473,
  "گدکیش": 2474,
  "دی راولپنڈ": 2475,
  "سلطانز": 2476,
  "گی عابد": 2477,
  "غیرقانون": 2478,
  "تھا نعم": 2479,
  "کی عابد": 2480,
  "ہا ساتھ": 2481,
  "مکیش": 2482,
  "چھابڑ": 2483,
  "وقار": 2484,
  "رائٹر": 2485,
  "رام": 2486,
  "راگھو": 2487,
  "گہرائ": 2488,
  "کمال": 2489,
  "فن": 2490,
  "ہی ابھیرج": 2491,
  "ناگ": 2492,
  "ارمرڈ": 2493,
  "اچھلی": 2494,
  "لادن": 2495,
  "ترک": 2496,
  "شدت": 2497,
  "مشتعل": 2498,
  "تھا ورلڈ": 2499,
  "ٹیررازم": 2500,
  "انسائیکلوپیڈا": 2501,
  "اف": 2502,
  "پولیٹیکل": 2503,
  "وائلنس": 2504,
  "فرام": 2505,
  "اینشنٹ": 2506,
  "جیمز": 2507,
  "سائمنٹ": 2508,
  "ہی سب": 2509,
  "لاسز": 2510,
  "کیپسیٹ": 2511,
  "ہا ماہرین": 2512,
  "امک": 2513,
  "رائج": 2514,
  "مثل": 2515,
  "ضرورا": 2516,
  "ہی دی": 2517,
  "انٹیمیس": 2518,
  "کیوریٹر": 2519,
  "سروگیس": 2520,
  "پیکج": 2521,
  "کوچز": 2522,
  "سیشنز": 2523,
  "بندرگاہ": 2524,
  "پرنس": 2525,
  "استقبال": 2526,
  "بکنگھم": 2527,
  "پیلس": 2528,
  "دیا دستاویز": 2529,
  "شخصا": 2530,
  "گی بعض": 2531,
  "مبصرین": 2532,
  "نیدر": 2533,
  "لینڈز": 2534,
  "سنہال": 2535,
  "شیڈول": 2536,
  "چروا": 2537,
  "بنکروں": 2538,
  "گولوں": 2539,
  "بندوق": 2540,
  "کارتوس": 2541,
  "برف": 2542,
  "آئی میجر": 2543,
  "کماؤن": 2544,
  "بٹالین": 2545,
  "چارل": 2546,
  "سپاہ": 2547,
  "تھی یادیو": 2548,
  "گولہ": 2549,
  "قیاس": 2550,
  "آرائ": 2551,
  "ملا فرید": 2552,
  "زلم": 2553,
  "کورحم": 2554,
  "چاہا جان": 2555,
  "اچکز": 2556,
  "محسن": 2557,
  "نقو": 2558,
  "شکرگزار": 2559,
  "گا کیا": 2560,
  "مکھ": 2561,
  "تشبیہ": 2562,
  "دی خواتین": 2563,
  "کورا": 2564,
  "کرپٹو": 2565,
  "ایکسچینج": 2566,
  "مالیت": 2567,
  "کوائن": 2568,
  "قلیل": 2569,
  "گا دراصل": 2570,
  "انعام": 2571,
  "جمعہ": 2572,
  "کوائنز": 2573,
  "مدمقابل": 2574,
  "تماشائ": 2575,
  "انتہ": 2576,
  "گراؤنڈ": 2577,
  "ایئرلائنز": 2578,
  "ابتد": 2579,
  "تنگ": 2580,
  "کی انھ": 2581,
  "اغو": 2582,
  "دھم": 2583,
  "ہی ادھر": 2584,
  "ڈسڑکٹ": 2585,
  "مشتاق": 2586,
  "سوموار": 2587,
  "نصراللہ": 2588,
  "سلاخ": 2589,
  "گردن": 2590,
  "لپٹ": 2591,
  "سکا بڑی": 2592,
  "جال": 2593,
  "ہی پچھ": 2594,
  "دھات": 2595,
  "یک": 2596,
  "بلاک": 2597,
  "ترمیم": 2598,
  "وفاق": 2599,
  "دستگیر": 2600,
  "مقدار": 2601,
  "دی اسرائیل": 2602,
  "چلاا": 2603,
  "ہا اسا": 2604,
  "ہیومینٹیرین": 2605,
  "جاس جی": 2606,
  "جگ": 2607,
  "لمب": 2608,
  "فاصلہ": 2609,
  "خزانہ": 2610,
  "ہا جون": 2611,
  "قطر": 2612,
  "ایئر": 2613,
  "فورس": 2614,
  "میراج": 2615,
  "رفال": 2616,
  "عارض": 2617,
  "کھیل آخر": 2618,
  "ملے": 2619,
  "پریم": 2620,
  "جسپریت": 2621,
  "بمراہ": 2622,
  "نومولود": 2623,
  "تحفہ": 2624,
  "دیا اسی": 2625,
  "پلا": 2626,
  "ہنس": 2627,
  "آا اس": 2628,
  "کھیلن": 2629,
  "کمان": 2630,
  "مول": 2631,
  "گا گوہر": 2632,
  "منع": 2633,
  "شاندار": 2634,
  "کارگرد": 2635,
  "دکھان": 2636,
  "تھا محنت": 2637,
  "اشتعال": 2638,
  "انگیز": 2639,
  "عناصر": 2640,
  "دیا حکومت": 2641,
  "نیپ": 2642,
  "ملوث": 2643,
  "سکی جمعہ": 2644,
  "توافغ": 2645,
  "سردار": 2646,
  "داؤد": 2647,
  "اجمل": 2648,
  "ہا اجمل": 2649,
  "جائی صدر": 2650,
  "پیروکار": 2651,
  "ہا روتھشیلڈ": 2652,
  "ناراض": 2653,
  "ریپبلکن": 2654,
  "ہی ٹرمپ": 2655,
  "اٹارن": 2656,
  "پام": 2657,
  "بونڈ": 2658,
  "کوٹھڑ": 2659,
  "حواس": 2660,
  "گا کو": 2661,
  "سپیشلسٹ": 2662,
  "ڈینٹسٹ": 2663,
  "سہی": 2664,
  "بتیس": 2665,
  "انچ": 2666,
  "کرو": 2667,
  "دو ای": 2668,
  "دستور": 2669,
  "شعر": 2670,
  "حبیب": 2671,
  "جالب": 2672,
  "سیا": 2673,
  "ہی کیا": 2674,
  "بحری": 2675,
  "مائنز": 2676,
  "ہی سمندر": 2677,
  "سرنگ": 2678,
  "پاک": 2679,
  "فعال": 2680,
  "ہا فاکس": 2681,
  "ہا وٹال": 2682,
  "ہلات": 2683,
  "لگائی": 2684,
  "ربڑ": 2685,
  "گولیاں": 2686,
  "کینن": 2687,
  "کی ان": 2688,
  "گا ایک": 2689,
  "ہوا ان": 2690,
  "مصروف": 2691,
  "بزنس": 2692,
  "ایپل": 2693,
  "ڈیل": 2694,
  "پراعتماد": 2695,
  "اشون": 2696,
  "آش": 2697,
  "سپنرز": 2698,
  "نک": 2699,
  "اندھ": 2700,
  "تھا بینا": 2701,
  "چارلس": 2702,
  "بونیٹ": 2703,
  "سنڈروم": 2704,
  "تجرب": 2705,
  "تھا دل": 2706,
  "نشان": 2707,
  "سرینڈر": 2708,
  "یروشلم": 2709,
  "ہو انھ": 2710,
  "قیام": 2711,
  "اکارڈ": 2712,
  "سپیکٹرم": 2713,
  "لائسنس": 2714,
  "کارپوریٹ": 2715,
  "فلاح": 2716,
  "گا سنیچر": 2717,
  "گیا میر": 2718,
  "تھا انڈین": 2719,
  "جدت": 2720,
  "سامان": 2721,
  "سیاق": 2722,
  "سباق": 2723,
  "تھا میر": 2724,
  "نہی نیوز": 2725,
  "پکڑ می": 2726,
  "لکھ سچن": 2727,
  "ٹکٹ": 2728,
  "کی می": 2729,
  "انتظار": 2730,
  "ربو": 2731,
  "پورہ": 2732,
  "گیا پوکھر": 2733,
  "دہل": 2734,
  "بس": 2735,
  "ہی تقریب": 2736,
  "عکس": 2737,
  "کشید": 2738,
  "عروج": 2739,
  "تھا بیجنگ": 2740,
  "دلا": 2741,
  "لام": 2742,
  "ناخوش": 2743,
  "تبت": 2744,
  "نجی": 2745,
  "گڈ": 2746,
  "مارننگ": 2747,
  "میزب": 2748,
  "راویت": 2749,
  "بتاا موضوع": 2750,
  "تذکرہ": 2751,
  "پلڑ": 2752,
  "جھ": 2753,
  "سک روس": 2754,
  "تجربات": 2755,
  "ہا بیلسٹک": 2756,
  "میزائلز": 2757,
  "راڈار": 2758,
  "لگان": 2759,
  "نہر": 2760,
  "گی جنور": 2761,
  "لپکن": 2762,
  "یہانٹرویوبہت": 2763,
  "ہی ہمار": 2764,
  "کرد لبن": 2765,
  "تھی شاہین": 2766,
  "ظفر": 2767,
  "انفراد": 2768,
  "شائست": 2769,
  "چاہا وہ": 2770,
  "عادت": 2771,
  "ناپسند": 2772,
  "کھلم": 2773,
  "تعصب": 2774,
  "آجو": 2775,
  "سنگر": 2776,
  "براس": 2777,
  "گیا کالعدم": 2778,
  "ریولوشنر": 2779,
  "ڈھانچہ": 2780,
  "ونگز": 2781,
  "کش": 2782,
  "علیحدہ": 2783,
  "بریگیڈ": 2784,
  "ٹارگٹ": 2785,
  "کلنگ": 2786,
  "اغواء": 2787,
  "کاروائ": 2788,
  "ملازمین": 2789,
  "بدسلو": 2790,
  "لیوین": 2791,
  "تھا دیہاڑ": 2792,
  "تھا گھر": 2793,
  "تھا کہت": 2794,
  "گا چار": 2795,
  "گیا اٹل": 2796,
  "حادث": 2797,
  "امی": 2798,
  "صدمہ": 2799,
  "تھا می": 2800,
  "تھا وزیر": 2801,
  "صوبا": 2802,
  "آگرچہ": 2803,
  "حامل": 2804,
  "سیٹس": 2805,
  "سٹریمنگ": 2806,
  "کلاؤڈ": 2807,
  "ہا وزارت": 2808,
  "خوف": 2809,
  "سون": 2810,
  "تھا بچا": 2811,
  "سہم": 2812,
  "کبھار": 2813,
  "تھی نوش": 2814,
  "داخ": 2815,
  "جوڈیشل": 2816,
  "کمپلیکس": 2817,
  "دفاتر": 2818,
  "کلیئر": 2819,
  "سپار": 2820,
  "سپیس": 2821,
  "اپر": 2822,
  "ایٹماسفئیر": 2823,
  "کمیونیکیشن": 2824,
  "ہا سیٹلائیٹ": 2825,
  "شی": 2826,
  "چانگ": 2827,
  "لانچ": 2828,
  "مواصلات": 2829,
  "ہا سپار": 2830,
  "دراز": 2831,
  "شان": 2832,
  "مسعود": 2833,
  "افتخار": 2834,
  "شکیل": 2835,
  "وسیم": 2836,
  "ہی زیادہ": 2837,
  "ہی ابتدا": 2838,
  "ہوا کمزور": 2839,
  "بڑ": 2840,
  "آداب": 2841,
  "حرمت": 2842,
  "بھول وسائل": 2843,
  "مقتدر": 2844,
  "دی اگر": 2845,
  "چنانچہ": 2846,
  "لفظا": 2847,
  "دی کرس": 2848,
  "مٹھ": 2849,
  "چاپی": 2850,
  "مالش": 2851,
  "پالش": 2852,
  "چاہا کسی": 2853,
  "کب": 2854,
  "پینٹر": 2855,
  "تھی سب": 2856,
  "کرتار": 2857,
  "ملا سونو": 2858,
  "تھا کوئٹہ": 2859,
  "کاظم": 2860,
  "پشتون": 2861,
  "کشیدہ": 2862,
  "آیا تحریک": 2863,
  "آب": 2864,
  "ائیر": 2865,
  "چیفس": 2866,
  "پڑھت": 2867,
  "تھا نتیجت": 2868,
  "کھلنا": 2869,
  "سلہٹ": 2870,
  "راجشاہ": 2871,
  "ہا انڈا": 2872,
  "ویدودو": 2873,
  "ہی رفال": 2874,
  "چوبیس": 2875,
  "ریڈار": 2876,
  "دورانیہ": 2877,
  "ہی وزارت": 2878,
  "ہا ایکشن": 2879,
  "بلکل": 2880,
  "وقفہ": 2881,
  "لین یہ": 2882,
  "ایشون": 2883,
  "بیٹسمین": 2884,
  "امپائر": 2885,
  "رخ": 2886,
  "سوئچ": 2887,
  "ہٹ": 2888,
  "ریورس": 2889,
  "فلماا": 2890,
  "ایڈٹ": 2891,
  "اپلوڈ": 2892,
  "ایمل": 2893,
  "گئی ایمل": 2894,
  "ہوگا جوڑ": 2895,
  "کی تو": 2896,
  "تجسس": 2897,
  "گاہک": 2898,
  "برٹش": 2899,
  "نوجو": 2900,
  "کیریئر": 2901,
  "نوکر": 2902,
  "ایڈوائزر": 2903,
  "کیو": 2904,
  "یوجین": 2905,
  "گیلر": 2906,
  "ہاؤزر": 2907,
  "ورتھ": 2908,
  "جائز": 2909,
  "تھی ایتھرٹن": 2910,
  "ہوگا": 2911,
  "ہو لیکن": 2912,
  "ہا اسرائیل": 2913,
  "عزہ": 2914,
  "کمیونٹیز": 2915,
  "سوا": 2916,
  "چارہ": 2917,
  "ہوگا تو": 2918,
  "تناظر": 2919,
  "ہا اور": 2920,
  "تکالیف": 2921,
  "لیڈر": 2922,
  "نہی غزہ": 2923,
  "اذیت": 2924,
  "ایڈیشن": 2925,
  "نقاب": 2926,
  "کی اگر": 2927,
  "دلدل": 2928,
  "حامیوں": 2929,
  "حجم": 2930,
  "پلیئنگ": 2931,
  "الیون": 2932,
  "کھلان": 2933,
  "ہوگا ٹیم": 2934,
  "بادل": 2935,
  "گا ایران": 2936,
  "شاھد": 2937,
  "جیرانیئم": 2938,
  "ہا دھماکہ": 2939,
  "اڑ": 2940,
  "ملا ہدف": 2941,
  "ٹکرا": 2942,
  "دھماکہ": 2943,
  "پھٹ": 2944,
  "نتج": 2945,
  "ہا شاھد": 2946,
  "رپورٹر": 2947,
  "سائمن": 2948,
  "سٹون": 2949,
  "مانچسٹر": 2950,
  "فینز": 2951,
  "بخوب": 2952,
  "کرسٹیانو": 2953,
  "رونالڈو": 2954,
  "پرواہ": 2955,
  "کرتا سنہ": 2956,
  "اولڈ": 2957,
  "ٹریفورڈ": 2958,
  "رخصت": 2959,
  "سہولیات": 2960,
  "ڈھانچ": 2961,
  "ایرک": 2962,
  "ٹین": 2963,
  "یمن": 2964,
  "تنظا": 2965,
  "ہی گذشتہ": 2966,
  "تہر": 2967,
  "حقیق": 2968,
  "کثیر": 2969,
  "منزلہ": 2970,
  "دی نج": 2971,
  "اخلاق": 2972,
  "گا بس": 2973,
  "آدرش": 2974,
  "وقوف": 2975,
  "مت": 2976,
  "کیج": 2977,
  "خناس": 2978,
  "ڈیٹس": 2979,
  "عورت": 2980,
  "غریب": 2981,
  "چاہتی": 2982,
  "ہ ،تصویر": 2983,
  "محروم": 2984,
  "جاوید": 2985,
  "میانداد": 2986,
  "انضمام": 2987,
  "یونس": 2988,
  "یوسف": 2989,
  "رہا جنوب": 2990,
  "ڈومیسٹک": 2991,
  "صلو": 2992,
  "سلیکشن": 2993,
  "ہا سلیکشن": 2994,
  "کوچنگ": 2995,
  "مینیجمنٹ": 2996,
  "ہا احس": 2997,
  "حماد": 2998,
  "سمیع": 2999,
  "اسلم": 3000,
  "ہا سیریبریانس": 3001,
  "عریض": 3002,
  "جنگل": 3003,
  "لیمن": 3004,
  "کوپیانسک": 3005,
  "پھی": 3006,
  "کمانڈر": 3007,
  "تشویشناک": 3008,
  "اولیکسینڈر": 3009,
  "سرس": 3010,
  "منظم": 3011,
  "عرف": 3012,
  "راجستھ": 3013,
  "رہا وہ": 3014,
  "بچہ": 3015,
  "تھا بعد": 3016,
  "کمشنڈ": 3017,
  "ولی": 3018,
  "اینک": 3019,
  "تھی یاد": 3020,
  "فرنچائزز": 3021,
  "بالترتیب": 3022,
  "سننس": 3023,
  "دیا اس": 3024,
  "ڈرا": 3025,
  "گیا پہ": 3026,
  "بنا افغانست": 3027,
  "عظمت": 3028,
  "بریفنگ": 3029,
  "عہدیدار": 3030,
  "روئٹرز": 3031,
  "کشمیر": 3032,
  "میرپور": 3033,
  "ہا پہ": 3034,
  "ریح": 3035,
  "البتہ": 3036,
  "ہا جنور": 3037,
  "تھی پاکست": 3038,
  "صوبہ": 3039,
  "سندھ": 3040,
  "اقر": 3041,
  "جیوان": 3042,
  "اتر": 3043,
  "پردیش": 3044,
  "الہ": 3045,
  "ملائم": 3046,
  "اگل": 3047,
  "لمحہ": 3048,
  "نکال یہ": 3049,
  "سائنسدان": 3050,
  "سیار": 3051,
  "بلین": 3052,
  "ٹکراا": 3053,
  "ٹکراو": 3054,
  "تھیا": 3055,
  "کائنات": 3056,
  "قربان": 3057,
  "ہا طبی": 3058,
  "مہلک": 3059,
  "ہی سلم": 3060,
  "افضل": 3061,
  "ڈیزائننگ": 3062,
  "مارکیٹنگ": 3063,
  "سٹریٹیج": 3064,
  "ملبوس": 3065,
  "جائی اس": 3066,
  "تکنا": 3067,
  "ڈیزائنرز": 3068,
  "ہی انشال": 3069,
  "علو": 3070,
  "برانڈ": 3071,
  "کھاڈ": 3072,
  "ٹیکسٹائل": 3073,
  "ڈیزائنر": 3074,
  "ریکارڈز": 3075,
  "گیا ٹرمپ": 3076,
  "دیکھ مجھ": 3077,
  "گندہ": 3078,
  "ہا گولڈمین": 3079,
  "ساکس": 3080,
  "لیگل": 3081,
  "ہی ترجم": 3082,
  "ٹون": 3083,
  "فرٹو": 3084,
  "گولڈمین": 3085,
  "ہا عراق": 3086,
  "بچھ": 3087,
  "بحریہ": 3088,
  "مائن": 3089,
  "سوئیپرز": 3090,
  "تھی ایر": 3091,
  "آبنا": 3092,
  "ہرمز": 3093,
  "گزرگاہ": 3094,
  "ہا دنی": 3095,
  "مائع": 3096,
  "جوہان": 3097,
  "شوبرگ": 3098,
  "چھو": 3099,
  "کر نجی": 3100,
  "اشتہار": 3101,
  "مینیجر": 3102,
  "شبہ": 3103,
  "ساکھ": 3104,
  "آسک پولیس": 3105,
  "تعزیر": 3106,
  "دفعہ": 3107,
  "فحش": 3108,
  "تیاری": 3109,
  "کاٹ": 3110,
  "ہا البتہ": 3111,
  "سیب": 3112,
  "واش": 3113,
  "سراپ": 3114,
  "ازراہ": 3115,
  "تفنن": 3116,
  "ہا کا": 3117,
  "قبلاسلام": 3118,
  "سکوٹ": 3119,
  "بائی": 3120,
  "آلود": 3121,
  "بندھ": 3122,
  "پیٹ": 3123,
  "مشین": 3124,
  "گن": 3125,
  "ہا میجر": 3126,
  "ہا سی": 3127,
  "ریواڑ": 3128,
  "قصبہ": 3129,
  "تھا جنگ": 3130,
  "درہ": 3131,
  "کلیمین": 3132,
  "ماڈلز": 3133,
  "فرنٹ": 3134,
  "رضاکار": 3135,
  "اوزار": 3136,
  "ہوت ایک": 3137,
  "رضاگروپ": 3138,
  "پاولو": 3139,
  "ناروزن": 3140,
  "ڈیکو": 3141,
  "ڈیلر": 3142,
  "ملا پھر": 3143,
  "جھنڈ": 3144,
  "چچی": 3145,
  "ابو": 3146,
  "فراج": 3147,
  "ہاد": 3148,
  "العراق": 3149,
  "تھا صلاح": 3150,
  "ارشد": 3151,
  "ڈوگر": 3152,
  "تھا ارشد": 3153,
  "راکٹ": 3154,
  "ٹائمر": 3155,
  "گھڑیاں": 3156,
  "ڈیٹونیٹر": 3157,
  "ہوا وہ": 3158,
  "مانیٹرنگ": 3159,
  "نہاد": 3160,
  "اسلامیہ": 3161,
  "شاخ": 3162,
  "اٹھت": 3163,
  "عبدالسید": 3164,
  "چیلنج": 3165,
  "ہی تجزیہ": 3166,
  "اورکز": 3167,
  "رہی ای": 3168,
  "ایڈرانیلین": 3169,
  "دیا پیٹرک": 3170,
  "ہی پھر": 3171,
  "معجزات": 3172,
  "دھڑکن": 3173,
  "گیا لیکن": 3174,
  "رہا کوم": 3175,
  "یادداشت": 3176,
  "کھی اسی": 3177,
  "کھی آا": 3178,
  "عندیہ": 3179,
  "ریٹینشن": 3180,
  "ہا کراچ": 3181,
  "کیا کراچ": 3182,
  "رہا دون": 3183,
  "ملتے": 3184,
  "کھات": 3185,
  "رہا جب": 3186,
  "متوازن": 3187,
  "ہا ہمار": 3188,
  "آا سینئر": 3189,
  "ٹریڈ": 3190,
  "یونینز": 3191,
  "وائٹ": 3192,
  "تھا جس": 3193,
  "معطل": 3194,
  "رہی گذشتہ": 3195,
  "ہی شردھ": 3196,
  "پیسہ": 3197,
  "کمات": 3198,
  "ہی اگرچہ": 3199,
  "تلاف": 3200,
  "نجم": 3201,
  "سیٹھ": 3202,
  "انتباہ": 3203,
  "قارئین": 3204,
  "وزیرآباد": 3205,
  "ملحقہ": 3206,
  "قصب": 3207,
  "دھونکل": 3208,
  "زمیندار": 3209,
  "گھرا": 3210,
  "فیملیز": 3211,
  "گرین": 3212,
  "سگنل": 3213,
  "تھی کچھ": 3214,
  "کیا بی": 3215,
  "توحید": 3216,
  "سکت ایس": 3217,
  "یکجہت": 3218,
  "کیا سنہ": 3219,
  "شمع": 3220,
  "انعقاد": 3221,
  "رہا بعد": 3222,
  "تیانانمن": 3223,
  "ہو ،تصویر": 3224,
  "پینگ": 3225,
  "گئی حنا": 3226,
  "پران": 3227,
  "پارٹنر": 3228,
  "چلی": 3229,
  "جلدی": 3230,
  "دی حنا": 3231,
  "سحر": 3232,
  "جکڑ": 3233,
  "منگیتر": 3234,
  "تھا چین": 3235,
  "تبصرہ": 3236,
  "گیا سطح": 3237,
  "تھی تاہم": 3238,
  "مہا": 3239,
  "یودھ": 3240,
  "مورچ": 3241,
  "تھا پھر": 3242,
  "گیا تو": 3243,
  "تھی ترجم": 3244,
  "ہینڈلز": 3245,
  "کیا انھ": 3246,
  "دیا دفتر": 3247,
  "تھا وحید": 3248,
  "عمان": 3249,
  "مصنفین": 3250,
  "دی فخر": 3251,
  "کاکاخیل": 3252,
  "صدا": 3253,
  "ٹرانسمیشن": 3254,
  "ضلع": 3255,
  "خیبر": 3256,
  "کلچر": 3257,
  "دیا انھ": 3258,
  "ہا یادو": 3259,
  "آتا وہ": 3260,
  "لداخ": 3261,
  "آدھ": 3262,
  "ہوت چین": 3263,
  "چشول": 3264,
  "لیت ان": 3265,
  "شانتو": 3266,
  "قاصر": 3267,
  "گا انڈا": 3268,
  "گا پوسوبیک": 3269,
  "بدانتظام": 3270,
  "ہا حالانکہ": 3271,
  "دستیابی": 3272,
  "لوڈ": 3273,
  "کوڈ": 3274,
  "ہی مثال": 3275,
  "ہی یاد": 3276,
  "ڈبل": 3277,
  "تھی بدھ": 3278,
  "طفیل": 3279,
  "لی ،تصویر": 3280,
  "اعجاز": 3281,
  "سٹریمز": 3282,
  "تشہیر": 3283,
  "کی ہمار": 3284,
  "تحقیق": 3285,
  "ممبرز": 3286,
  "ایڈیٹ": 3287,
  "سٹریم": 3288,
  "کلپس": 3289,
  "لائبریر": 3290,
  "مقررہ": 3291,
  "ہی می": 3292,
  "آرکائیو": 3293,
  "دیکھی": 3294,
  "ہی اا": 3295,
  "سبسکرائبرز": 3296,
  "فنکشن": 3297,
  "تبصر": 3298,
  "مہمان": 3299,
  "انخل": 3300,
  "مقبولیت": 3301,
  "لیول": 3302,
  "سیلیکٹ": 3303,
  "اپریل": 3304,
  "ہی چین": 3305,
  "بیورو": 3306,
  "سٹیٹسٹکس": 3307,
  "اوسط": 3308,
  "تھی چین": 3309,
  "الیکٹرانکس": 3310,
  "ہواقیانگب": 3311,
  "خریدن": 3312,
  "لگا عدالت": 3313,
  "پورن": 3314,
  "تھا پاکستان": 3315,
  "ہا خیال": 3316,
  "زدہ": 3317,
  "امین": 3318,
  "بقا": 3319,
  "دکاندار": 3320,
  "چیکوسلواکیہ": 3321,
  "ناظم": 3322,
  "الامور": 3323,
  "سوویت": 3324,
  "مجاہدین": 3325,
  "گی ایک": 3326,
  "ہی سمیع": 3327,
  "ڈیلرز": 3328,
  "جہادی": 3329,
  "جنگجو": 3330,
  "تھا سمیع": 3331,
  "طالبان": 3332,
  "ہا او": 3333,
  "جندال": 3334,
  "گلوبل": 3335,
  "کو انھ": 3336,
  "ہا کسی": 3337,
  "منعقد": 3338,
  "سیکیورٹ": 3339,
  "ملن": 3340,
  "گزشتہ": 3341,
  "ڈنمارک": 3342,
  "ناروے": 3343,
  "سویڈن": 3344,
  "لتھوینا": 3345,
  "ہی مغرب": 3346,
  "سولین": 3347,
  "بھیج یہ": 3348,
  "اڑاا": 3349,
  "ہا مغرب": 3350,
  "کریملن": 3351,
  "بسر": 3352,
  "ہا ورلڈ": 3353,
  "غذا": 3354,
  "عدم": 3355,
  "ذریعہ اقوام": 3356,
  "المدت": 3357,
  "برسلز": 3358,
  "لیج": 3359,
  "گا برطانیہ": 3360,
  "خصوص": 3361,
  "دستہ": 3362,
  "بیلجیئم": 3363,
  "لینڈنگ": 3364,
  "پشوپت": 3365,
  "ناتھ": 3366,
  "ہوئا ایک": 3367,
  "ڈرائیور": 3368,
  "گا ہمار": 3369,
  "ہا مجھ": 3370,
  "ڈال شاد": 3371,
  "تبدیلی": 3372,
  "ہونے": 3373,
  "لگا ونٹر": 3374,
  "بلیوز": 3375,
  "سیزنل": 3376,
  "افیکٹیو": 3377,
  "آرڈر": 3378,
  "تھا سیم": 3379,
  "ہا میر": 3380,
  "ہی زند": 3381,
  "بڑھاپ": 3382,
  "موت آخر": 3383,
  "نصب": 3384,
  "تھا سرکار": 3385,
  "عہد": 3386,
  "حلف": 3387,
  "پختون": 3388,
  "سٹوڈنٹس": 3389,
  "فیڈریشن": 3390,
  "افراسیاب": 3391,
  "گا نثار": 3392,
  "اسفندیار": 3393,
  "پیسیفک": 3394,
  "سرٹیفیکیشن": 3395,
  "ہا ریگولیٹر": 3396,
  "ہی طیارہ": 3397,
  "سٹیٹ": 3398,
  "اسسٹنٹ": 3399,
  "جگیشور": 3400,
  "بدعنوان": 3401,
  "چورا": 3402,
  "رشوت": 3403,
  "تھا جگیشور": 3404,
  "بقاا": 3405,
  "محاذ": 3406,
  "چیرنش": 3407,
  "میخائلو": 3408,
  "فیودوروف": 3409,
  "موثر": 3410,
  "ہو ہمار": 3411,
  "اصغر": 3412,
  "ہی عراق": 3413,
  "گی پردیس": 3414,
  "کاٹتا": 3415,
  "بندہ": 3416,
  "مزدور": 3417,
  "گوجرانوالہ": 3418,
  "کنگن": 3419,
  "رہائش": 3420,
  "منہاس": 3421,
  "اصغرعل": 3422,
  "کرم": 3423,
  "بصیرت": 3424,
  "پوسٹس": 3425,
  "برطانیہ": 3426,
  "شہرت": 3427,
  "پروفائل": 3428,
  "بیکہم": 3429,
  "ہا بروکلن": 3430,
  "پہچ": 3431,
  "فوٹوگراف": 3432,
  "پکا": 3433,
  "آزماا ان": 3434,
  "افوا": 3435,
  "گردش": 3436,
  "رہی مگر": 3437,
  "ہو اگر": 3438,
  "بدلت": 3439,
  "معروف": 3440,
  "معیشت": 3441,
  "بسواجیت": 3442,
  "انکشاف": 3443,
  "رکھ تاہم": 3444,
  "ہی دستاویز": 3445,
  "گلوکار": 3446,
  "ڈیوڈ": 3447,
  "کاپرفیلڈ": 3448,
  "گیا سابق": 3449,
  "ہی میوزیم": 3450,
  "سیوس": 3451,
  "بیراج": 3452,
  "تھی پتنگ": 3453,
  "جڑی": 3454,
  "آسم": 3455,
  "تھی اگر": 3456,
  "دشمن": 3457,
  "یونائیٹڈز": 3458,
  "شاداب": 3459,
  "پلاٹینم": 3460,
  "کیٹیگری": 3461,
  "ارشاد": 3462,
  "اندریس": 3463,
  "گوس": 3464,
  "گی کوئٹہ": 3465,
  "ابرار": 3466,
  "ہا ایئر": 3467,
  "کامبیٹ": 3468,
  "شوٹ": 3469,
  "فرسٹ": 3470,
  "مرض": 3471,
  "انٹیگریٹ": 3472,
  "می دوسر": 3473,
  "کیا جلال": 3474,
  "پشتو": 3475,
  "دری": 3476,
  "کاسٹرز": 3477,
  "تھا صحاف": 3478,
  "پروگرامز": 3479,
  "اضلاع": 3480,
  "مداح": 3481,
  "تھا افغ": 3482,
  "انیس": 3483,
  "کینیا": 3484,
  "لالچ": 3485,
  "تھا انسٹ": 3486,
  "سٹڈ": 3487,
  "وار": 3488,
  "کترین": 3489,
  "سٹیپانین": 3490,
  "بلدیات": 3491,
  "علاقا": 3492,
  "پروفیشنلز": 3493,
  "توڑ": 3494,
  "ہےتو": 3495,
  "گا وہ": 3496,
  "کرتب": 3497,
  "آئرلینڈ": 3498,
  "کیتھولک": 3499,
  "کنگزمین": 3500,
  "ہی بدھ": 3501,
  "فہیم": 3502,
  "اشرف": 3503,
  "اباد": 3504,
  "لیا نیلام": 3505,
  "نسیم": 3506,
  "وفد": 3507,
  "ادوار": 3508,
  "اندرون": 3509,
  "کمزرو": 3510,
  "برت وہ": 3511,
  "ہ لیکن": 3512,
  "پات": 3513,
  "ابھر پبلک": 3514,
  "نیو": 3515,
  "کاسل": 3516,
  "فولیو": 3517,
  "ٹینس": 3518,
  "ٹورز": 3519,
  "سپانسرشپ": 3520,
  "فٹبال": 3521,
  "باکسنگ": 3522,
  "فارمول": 3523,
  "ہا ملک": 3524,
  "فیف": 3525,
  "ہوا عمر": 3526,
  "رہا یہ": 3527,
  "آئںدہ": 3528,
  "شور": 3529,
  "متمول": 3530,
  "تھا عابد": 3531,
  "روزگار": 3532,
  "تای": 3533,
  "عابد": 3534,
  "فرنیچر": 3535,
  "ریستور": 3536,
  "ہی غیرقانون": 3537,
  "رہا اپ": 3538,
  "کھیلت مگر": 3539,
  "جنون": 3540,
  "تھا حسیب": 3541,
  "ہا رضا": 3542,
  "پہلوی": 3543,
  "بیٹے": 3544,
  "گی تاکہ": 3545,
  "ہو ان": 3546,
  "مکالم": 3547,
  "تلخ": 3548,
  "بھلان": 3549,
  "رہا خود": 3550,
  "بھٹو": 3551,
  "لگا اپن": 3552,
  "کتا": 3553,
  "ب": 3554,
  "جرن": 3555,
  "الیونمنٹ": 3556,
  "مزار": 3557,
  "قائد": 3558,
  "ضابط": 3559,
  "رکھا": 3560,
  "پڑا نیلام": 3561,
  "کشمکش": 3562,
  "ہوئا کوئٹہ": 3563,
  "مسکرات": 3564,
  "تھی کھلاڑ": 3565,
  "آپس": 3566,
  "تھا اا": 3567,
  "ٹیمز": 3568,
  "روایت": 3569,
  "بنا یہی": 3570,
  "مہر": 3571,
  "ممتاز": 3572,
  "کھیپ": 3573,
  "کیریبیئن": 3574,
  "گیا ایک": 3575,
  "ذرا": 3576,
  "سوچا": 3577,
  "مقدس": 3578,
  "گند": 3579,
  "گیا سنہ": 3580,
  "ڈھانپ": 3581,
  "ڈھا": 3582,
  "پڑوس": 3583,
  "رہی بیان": 3584,
  "بگاڑ": 3585,
  "سیاستد": 3586,
  "دیمک": 3587,
  "ویس": 3588,
  "سکھا": 3589,
  "ہا بعد": 3590,
  "کالز": 3591,
  "برفان": 3592,
  "تھا منش": 3593,
  "گوندل": 3594,
  "پوچھ مجھ": 3595,
  "علم": 3596,
  "بتات میر": 3597,
  "گیا می": 3598,
  "گلہ": 3599,
  "کر میر": 3600,
  "اجڑ": 3601,
  "سکت انڈین": 3602,
  "ریو": 3603,
  "گانگول": 3604,
  "آئندہ": 3605,
  "بڑھان": 3606,
  "گا دہل": 3607,
  "خواہش": 3608,
  "دہان": 3609,
  "پوائنٹ": 3610,
  "کیلیبر": 3611,
  "گلوک": 3612,
  "پستول": 3613,
  "راؤنڈز": 3614,
  "راؤنڈ": 3615,
  "گلوگ": 3616,
  "نائن": 3617,
  "آرمرڈ": 3618,
  "ملی دستاویز": 3619,
  "لقم": 3620,
  "اسلحے": 3621,
  "تھی نوٹ": 3622,
  "سبز": 3623,
  "گھاس": 3624,
  "تھا ابھ": 3625,
  "مجسم": 3626,
  "محققین": 3627,
  "خانہ": 3628,
  "بدوش": 3629,
  "گی سعود": 3630,
  "مؤرخ": 3631,
  "ریاض": 3632,
  "کالم": 3633,
  "بدر": 3634,
  "صد": 3635,
  "جزیرہ": 3636,
  "ہی اونٹ": 3637,
  "خشک": 3638,
  "جھلست": 3639,
  "زندہ": 3640,
  "گڑھ": 3641,
  "سمھج": 3642,
  "آا بلوچست": 3643,
  "کارکن": 3644,
  "ہی تحریک": 3645,
  "تھی اپوزیشن": 3646,
  "لگا ای": 3647,
  "آا تاہم": 3648,
  "لیفٹیننٹ": 3649,
  "شریف": 3650,
  "ویریفا": 3651,
  "گنبد": 3652,
  "لگایا": 3653,
  "گیا جب": 3654,
  "متق": 3655,
  "گرینڈ": 3656,
  "جیور": 3657,
  "کریں": 3658,
  "بشرطیکہ": 3659,
  "جا اس": 3660,
  "حص": 3661,
  "ہی کیوآنن": 3662,
  "کیپیٹل": 3663,
  "ہل": 3664,
  "تھا گزشتہ": 3665,
  "عین": 3666,
  "سرو": 3667,
  "ریلیجن": 3668,
  "نیورو": 3669,
  "کروا یہ": 3670,
  "اینستھیزا": 3671,
  "کھوپڑ": 3672,
  "چاک": 3673,
  "ٹریجمنل": 3674,
  "نروو": 3675,
  "سکا اس": 3676,
  "پیچیدگ": 3677,
  "چہر": 3678,
  "سماعت": 3679,
  "فالج": 3680,
  "حتا": 3681,
  "بد": 3682,
  "گی ،تصویر": 3683,
  "ہائ": 3684,
  "ہا ہائ": 3685,
  "پچیس": 3686,
  "گنا": 3687,
  "ہا ایر": 3688,
  "کیفیت": 3689,
  "گی ان": 3690,
  "محنت": 3691,
  "سدب": 3692,
  "گا عائشہ": 3693,
  "ربیعہ": 3694,
  "احسن": 3695,
  "ماحولیات": 3696,
  "آلودگی": 3697,
  "گلیشیئرز": 3698,
  "پگھل": 3699,
  "آبی": 3700,
  "درپیش": 3701,
  "تھا روہت": 3702,
  "لائق": 3703,
  "روہت": 3704,
  "میڈرڈ": 3705,
  "بنزیم": 3706,
  "پرتگال": 3707,
  "روبن": 3708,
  "نیویس": 3709,
  "ٹائٹلز": 3710,
  "جیتت": 3711,
  "دیکھ ،تصویر": 3712,
  "بگ": 3713,
  "کی اسی": 3714,
  "ملین": 3715,
  "پاؤنڈ": 3716,
  "عاطف": 3717,
  "ران": 3718,
  "من": 3719,
  "انوار": 3720,
  "بنتی": 3721,
  "آفر": 3722,
  "بازار": 3723,
  "تھا کامر": 3724,
  "بخار": 3725,
  "بحال": 3726,
  "عزائم": 3727,
  "سمجھوتہ": 3728,
  "جا وہ": 3729,
  "قرض": 3730,
  "ہی علی": 3731,
  "سٹاک": 3732,
  "سیٹلمنٹ": 3733,
  "ادائیگ": 3734,
  "ری": 3735,
  "سٹرکچرنگ لیکن": 3736,
  "شریعت": 3737,
  "اپیل": 3738,
  "معتدل": 3739,
  "متوسط": 3740,
  "چکی انھ": 3741,
  "گی چا": 3742,
  "قیادت": 3743,
  "گا عمل": 3744,
  "اوپننگ": 3745,
  "پارٹنرشپ": 3746,
  "کھیل تاہم": 3747,
  "گری": 3748,
  "زرد": 3749,
  "پانچو": 3750,
  "اننگز": 3751,
  "رکھ سب": 3752,
  "ہوا تاہم": 3753,
  "گا ریبا": 3754,
  "لگتی": 3755,
  "خالد": 3756,
  "شیخ": 3757,
  "پھل": 3758,
  "بہر": 3759,
  "بچت": 3760,
  "رہا دو": 3761,
  "ایبٹ": 3762,
  "نکل مشرف": 3763,
  "گیا یہ": 3764,
  "چھپ": 3765,
  "تھا مقررہ": 3766,
  "پوش": 3767,
  "لیا اس": 3768,
  "محافظ": 3769,
  "حالت": 3770,
  "آتش": 3771,
  "موٹر": 3772,
  "اشی": 3773,
  "آزادانہ": 3774,
  "سکت ان": 3775,
  "پہنچا": 3776,
  "جلی": 3777,
  "تھی کوئٹہ": 3778,
  "مستونگ": 3779,
  "قل": 3780,
  "ہا پتنگ": 3781,
  "ہا فی": 3782,
  "ایجاد": 3783,
  "ہوئا شاعر": 3784,
  "مساج لٹنک": 3785,
  "معذرت": 3786,
  "گھٹا": 3787,
  "فرانزک": 3788,
  "جائےگا": 3789,
  "گا خیال": 3790,
  "کور": 3791,
  "ہائیکورٹ": 3792,
  "ہراس": 3793,
  "تھا سربجیت": 3794,
  "چھاپہ": 3795,
  "زندگی": 3796,
  "آؤٹ": 3797,
  "لگا انھ": 3798,
  "میراتھن": 3799,
  "مراکش": 3800,
  "ہائیکنگ": 3801,
  "کی لیکن": 3802,
  "سرانجام": 3803,
  "صحن": 3804,
  "برفا": 3805,
  "ٹھنڈ": 3806,
  "غسل ان": 3807,
  "پینشن": 3808,
  "منسوخ": 3809,
  "ہی پرنس": 3810,
  "ویلز": 3811,
  "ارتھ": 3812,
  "پراجیکٹ": 3813,
  "فنڈنگ": 3814,
  "چیریٹ": 3815,
  "کھنہ": 3816,
  "تھامس": 3817,
  "میس": 3818,
  "راجیو": 3819,
  "نگران": 3820,
  "جھٹ": 3821,
  "شارٹ": 3822,
  "سرکٹ": 3823,
  "تہوار": 3824,
  "یکم": 3825,
  "گئیں": 3826,
  "تھی لاہور": 3827,
  "ڈپٹ": 3828,
  "انسپکٹر": 3829,
  "کامر": 3830,
  "آندر": 3831,
  "گیل": 3832,
  "میتھو": 3833,
  "ہیڈن": 3834,
  "رکی": 3835,
  "پونٹنگ": 3836,
  "بیٹس": 3837,
  "ڈینس": 3838,
  "للی": 3839,
  "ایلومینیم": 3840,
  "کاؤنٹ": 3841,
  "ایسیکس": 3842,
  "مروجہ": 3843,
  "گنوا": 3844,
  "تھا ناٹنگھم": 3845,
  "شائر": 3846,
  "فتح": 3847,
  "اوائل": 3848,
  "لی ایپسٹین": 3849,
  "ڈالن": 3850,
  "چاہا ای": 3851,
  "گرامر": 3852,
  "کٹ": 3853,
  "پیسٹ": 3854,
  "ایریان": 3855,
  "ہا بنگلہ": 3856,
  "صفر": 3857,
  "ٹیرف": 3858,
  "ہا یہی": 3859,
  "سپلائر": 3860,
  "پیت": 3861,
  "تھا کچھ": 3862,
  "سک تن": 3863,
  "تھا حالت": 3864,
  "جاسکت": 3865,
  "ہا عزیر": 3866,
  "گنت": 3867,
  "نہی اس": 3868,
  "نڈھال": 3869,
  "تھا یاد": 3870,
  "پیرس": 3871,
  "تقریر": 3872,
  "مقبوضہ": 3873,
  "کنار": 3874,
  "تھا اردن": 3875,
  "بیزلیل": 3876,
  "امن": 3877,
  "تھا تقی": 3878,
  "ماما": 3879,
  "بلات": 3880,
  "شش": 3881,
  "پنج": 3882,
  "دھوکہ": 3883,
  "اورغلط": 3884,
  "ہی پولیس": 3885,
  "بائبل": 3886,
  "یہودیہ": 3887,
  "سامرہ": 3888,
  "سینائی": 3889,
  "پہاڑ": 3890,
  "تقی": 3891,
  "معاشر": 3892,
  "رچا": 3893,
  "بسا": 3894,
  "ہا کم": 3895,
  "ہا پیر": 3896,
  "فیلڈ": 3897,
  "تھا حیران": 3898,
  "ہا ٹی": 3899,
  "جرما": 3900,
  "خراج": 3901,
  "تحسین": 3902,
  "ہا شیخ": 3903,
  "حسینہ": 3904,
  "سجیب": 3905,
  "واجد": 3906,
  "قربت": 3907,
  "ایکسپریس": 3908,
  "چاہا عوام": 3909,
  "سرزمین": 3910,
  "گی بی": 3911,
  "خراسان": 3912,
  "الیاس": 3913,
  "ہا دون": 3914,
  "بھائیوں": 3915,
  "شعیب": 3916,
  "ہزارگنج": 3917,
  "سکا ان": 3918,
  "چچا": 3919,
  "شبیر": 3920,
  "اے": 3921,
  "ین": 3922,
  "جوائنٹ": 3923,
  "محور": 3924,
  "پرنٹ": 3925,
  "میڈ": 3926,
  "فارمز": 3927,
  "ہا پی": 3928,
  "فیڈرل": 3929,
  "جرنلسٹس": 3930,
  "حامد": 3931,
  "اروند": 3932,
  "اترپردیش": 3933,
  "بھیواڑ": 3934,
  "ہی بڑی": 3935,
  "سکول": 3936,
  "ہی اروند": 3937,
  "قبلہ": 3938,
  "شرف": 3939,
  "زیارت": 3940,
  "ہی کا": 3941,
  "پوچھ": 3942,
  "گیا ہم": 3943,
  "گا ہم": 3944,
  "راحت": 3945,
  "نرم": 3946,
  "ہا نتائج": 3947,
  "برداشت": 3948,
  "اطمین": 3949,
  "فائر": 3950,
  "کھر": 3951,
  "قاتل": 3952,
  "ڈاگ": 3953,
  "کولوریکٹل": 3954,
  "ہا جہ": 3955,
  "الرٹ": 3956,
  "ٹیومر": 3957,
  "مقعد": 3958,
  "ہا حالیہ": 3959,
  "کیسز": 3960,
  "رجح": 3961,
  "دیکھں": 3962,
  "مبہم": 3963,
  "پیچیدہ": 3964,
  "ملشٹائن": 3965,
  "انٹیل": 3966,
  "امور": 3967,
  "ملیشا": 3968,
  "رویہ": 3969,
  "ہا بین": 3970,
  "سگنلنگ": 3971,
  "خالدہ": 3972,
  "ضیا": 3973,
  "ٹویٹ": 3974,
  "کیا ڈاکٹر": 3975,
  "پس": 3976,
  "پشت": 3977,
  "تخریب": 3978,
  "پلانٹ": 3979,
  "خلیج": 3980,
  "ہا واضح": 3981,
  "بوشھر": 3982,
  "کمرشل": 3983,
  "لا پولیس": 3984,
  "پب": 3985,
  "واٹس": 3986,
  "ایپ": 3987,
  "کیا گریٹر": 3988,
  "اشوک": 3989,
  "کمار": 3990,
  "ٹھہراا": 3991,
  "حملے": 3992,
  "معلومات": 3993,
  "کارگو": 3994,
  "آتشزدگی": 3995,
  "سبوتاژ": 3996,
  "ہی رو": 3997,
  "اطالو": 3998,
  "ایڈمرل": 3999,
  "جوزیپ": 4000,
  "کاوو": 4001,
  "اولین": 4002,
  "ہی اڈیالہ": 4003,
  "معائنوں": 4004,
  "گئی یاد": 4005,
  "مد": 4006,
  "نیپر": 4007,
  "پیز": 4008,
  "انکم": 4009,
  "فیول": 4010,
  "ایڈجسٹمنٹ": 4011,
  "چارجز": 4012,
  "ہی کپیسٹ": 4013,
  "لی دور": 4014,
  "لوسیان": 4015,
  "ایسکلیر": 4016,
  "تھی سی": 4017,
  "ہریسن": 4018,
  "سٹور": 4019,
  "کارٹن": 4020,
  "تھا اپ": 4021,
  "ہی ام": 4022,
  "تدفین": 4023,
  "اکرم": 4024,
  "مناسر": 4025,
  "حسیب": 4026,
  "موٹ": 4027,
  "رہا می": 4028,
  "تھا عثم": 4029,
  "سپیئر": 4030,
  "فریق": 4031,
  "متضاد": 4032,
  "بمبار": 4033,
  "ہا جبکہ": 4034,
  "گا ادھر": 4035,
  "ثان": 4036,
  "ہا سری": 4037,
  "روین": 4038,
  "وکرماراتھ": 4039,
  "نظرثان": 4040,
  "سکا سری": 4041,
  "جھڑپ": 4042,
  "پڑا وکیل": 4043,
  "وحمل": 4044,
  "تھی عثم": 4045,
  "نکھ": 4046,
  "ہی حسیب": 4047,
  "بلڈ": 4048,
  "چھلانگ": 4049,
  "عضو": 4050,
  "تناسل": 4051,
  "ہائیلورونک": 4052,
  "ایسڈ": 4053,
  "ہی اب": 4054,
  "ڈوپنگ": 4055,
  "واڈ": 4056,
  "ہی مطلوب": 4057,
  "ڈیرہ": 4058,
  "نواب": 4059,
  "اکبر": 4060,
  "تھا ڈیرہ": 4061,
  "نوابزادہ": 4062,
  "براہمدغ": 4063,
  "سوئٹزرلینڈ": 4064,
  "ہوگ وہ": 4065,
  "گپ": 4066,
  "شپ": 4067,
  "ہی جب": 4068,
  "جشن": 4069,
  "منات": 4070,
  "لائٹس": 4071,
  "شکایت": 4072,
  "ہی خواتین": 4073,
  "بدکردار": 4074,
  "طوائف": 4075,
  "نازیب": 4076,
  "القاب": 4077,
  "ژینگژو": 4078,
  "ڈیموکریٹس": 4079,
  "محکم": 4080,
  "تھا خیال": 4081,
  "باہم": 4082,
  "گا اکرام": 4083,
  "سہگل": 4084,
  "ہمسا": 4085,
  "ہی لہذ": 4086,
  "رہی وہ": 4087,
  "پالک": 4088,
  "پو": 4089,
  "برتھ": 4090,
  "سرٹیفکیٹ": 4091,
  "باپ": 4092,
  "پدورن": 4093,
  "گا پولیس": 4094,
  "کمشنر": 4095,
  "پراچ": 4096,
  "الیکشن": 4097,
  "گا سرکل": 4098,
  "انسپیکٹر": 4099,
  "وجا": 4100,
  "بابو": 4101,
  "رنگ": 4102,
  "شائقین": 4103,
  "خواب": 4104,
  "لیجنڈ": 4105,
  "ہلا": 4106,
  "دیا ایک": 4107,
  "پیار": 4108,
  "مشینر": 4109,
  "منگوان": 4110,
  "ڈیمانڈ": 4111,
  "پیکجز": 4112,
  "خریدت": 4113,
  "ماہانہ": 4114,
  "بلنگ": 4115,
  "منحصر": 4116,
  "ہا ای": 4117,
  "ہا حکومت": 4118,
  "درآمد": 4119,
  "مہن": 4120,
  "تھی انڈا": 4121,
  "کاج": 4122,
  "بالخصوص": 4123,
  "معاشرت": 4124,
  "پاؤں": 4125,
  "جائی بی": 4126,
  "رنویر": 4127,
  "دھورندھر": 4128,
  "وف": 4129,
  "فلمسٹار": 4130,
  "اگستھا": 4131,
  "نندرہ": 4132,
  "سراہ": 4133,
  "ووڈ": 4134,
  "امیتابھ": 4135,
  "بچن": 4136,
  "اکٹھ": 4137,
  "گا مقتولہ": 4138,
  "نعش": 4139,
  "سول": 4140,
  "بھجواا": 4141,
  "ناک": 4142,
  "منہ": 4143,
  "رک": 4144,
  "ٹوٹ": 4145,
  "گا پوسٹ": 4146,
  "ریپ": 4147,
  "گا ای": 4148,
  "ڈوگیرال": 4149,
  "وینکٹ": 4150,
  "روی": 4151,
  "لکشم": 4152,
  "پیاز": 4153,
  "گا فوربز": 4154,
  "ہی پوتن": 4155,
  "فائدہ": 4156,
  "کی روس": 4157,
  "ٹائیکون": 4158,
  "میخائل": 4159,
  "خودورکووس": 4160,
  "تھا جو": 4161,
  "جمہوریت": 4162,
  "دانشور": 4163,
  "ہی آسام": 4164,
  "ہا دائی": 4165,
  "لچکدار": 4166,
  "باڈ": 4167,
  "ٹائٹ": 4168,
  "انڈرویئر": 4169,
  "ہا قواعد": 4170,
  "گنجائش": 4171,
  "ہا پیمائش": 4172,
  "درمیان": 4173,
  "ہا مرد": 4174,
  "جزو": 4175,
  "نیچے": 4176,
  "رائٹ": 4177,
  "مارکس": 4178,
  "موز": 4179,
  "منقطع": 4180,
  "تحویل": 4181,
  "گا ٹنکوف": 4182,
  "ہا اولیگ": 4183,
  "نیویارک": 4184,
  "یرغمال": 4185,
  "پوتن": 4186,
  "کمپنی": 4187,
  "کفیت": 4188,
  "ہا ڈاکمر": 4189,
  "عوم": 4190,
  "پوزیشن": 4191,
  "ہا کن": 4192,
  "چھوڑت": 4193,
  "چوٹ": 4194,
  "انٹرایکٹو": 4195,
  "کوآپ": 4196,
  "پسندیدہ": 4197,
  "ہا جو": 4198,
  "سپن": 4199,
  "باؤلنگ": 4200,
  "گا نمیبا": 4201,
  "آدتیہ": 4202,
  "کیا اگرچہ": 4203,
  "ہی ہو": 4204,
  "شرمند": 4205,
  "ہ وہ": 4206,
  "تمہار": 4207,
  "فکر": 4208,
  "پوچھن": 4209,
  "زہریل": 4210,
  "ہی ایر": 4211,
  "بچھا": 4212,
  "ہی اگر": 4213,
  "ناگزیر": 4214,
  "گا بی": 4215,
  "لک": 4216,
  "دی اور": 4217,
  "عسکریت": 4218,
  "تفت": 4219,
  "مفرور": 4220,
  "زمانہ": 4221,
  "تھا ہم": 4222,
  "صحافیوں": 4223,
  "حاضر": 4224,
  "بطور": 4225,
  "ٹم": 4226,
  "پین": 4227,
  "ہیڈ": 4228,
  "تھا ٹیم": 4229,
  "پچاس": 4230,
  "ہا امریکہ": 4231,
  "خام": 4232,
  "برامد": 4233,
  "فروغ": 4234,
  "ہا معاہدہ": 4235,
  "فائد": 4236,
  "گا کی": 4237,
  "پیمانہ": 4238,
  "گا پروفیسر": 4239,
  "پنت": 4240,
  "کامیکاز": 4241,
  "ہی گیر": 4242,
  "شہروں": 4243,
  "ورکس": 4244,
  "فاصل": 4245,
  "ہی روس": 4246,
  "ہا واشنگٹن": 4247,
  "گرم": 4248,
  "خزا": 4249,
  "رہی پانچ": 4250,
  "بھڑک": 4251,
  "اٹھ اس": 4252,
  "تھا پرامن": 4253,
  "پرتشدد": 4254,
  "رہا سیاہ": 4255,
  "مظاہرین": 4256,
  "پٹرول": 4257,
  "پھینکے": 4258,
  "پارلیم": 4259,
  "دھاو": 4260,
  "ہی وکیل": 4261,
  "شاہراہ": 4262,
  "فاص": 4263,
  "کیشن": 4264,
  "ٹریفک": 4265,
  "تھا دوسر": 4266,
  "گلنگور": 4267,
  "لسٹنگ": 4268,
  "کیا بعد": 4269,
  "مان": 4270,
  "لالچی": 4271,
  "ظالم": 4272,
  "غاصب": 4273,
  "بھانپ": 4274,
  "پای بروس": 4275,
  "پامال": 4276,
  "گا ماہرین": 4277,
  "بورس": 4278,
  "منتخب": 4279,
  "ہوا ما": 4280,
  "مضمون": 4281,
  "ڈالت": 4282,
  "تھا مضمون": 4283,
  "محیط": 4284,
  "فٹنگز": 4285,
  "ایٹیلیئر": 4286,
  "کیا اس": 4287
}